Workbook
Name RangoDinamico: DESREF(Albums!#REF!,0,0,Albums!$AF$3,1)

Sheet GUÍA
A1: Este excel lo empecé el 17 de enero de 2026 con el objetivo de hacer 1000 reviews de álbumes | P1: 10.5
A2: Escribo esta guía por si en algún futuro se me olvida como funciona | O2: >8,9 | P2: 10
O3: >8,8 | P3: 9.5
A4: FLUJO DE REVIEW | O4: >8,7 | P4: 9
A5: 1. Hacer la review en la hoja Albums | O5: >8,5 | P5: 8.5
A6: 1.1 Todos los álbumes empiezan con un header así: * <Artista> - <Nombre álbum> | O6: >8 | P6: 8
A7: 1.2 El asterisco es obligatorio, sin él, el script ignora el álbum | O7: >7,5 | P7: 7.5
A8: 1.3 El guion separando el artista y el álbum también es obligatorio | O8: >7 | P8: 7
A9: 1.4 Esto implica que ni el artista ni el álbum pueden contener esos dos símbolos
A10: 1.5 En la celda justo debajo de la última canción (la que antes se dejaba vacía) escribir la línea de info:
A11: <año>, <subgéneros separados por comas>, <duración>
A12: Ejemplo: 1972, progressive rock, art rock, 1h 2m
A13: 1.6 Subgéneros: suelo poner los géneros principales del álbum que salgan en RYM.com (el script los pasa a minúsculas)
A14: 1.7 Duración con el formato <horas>h <minutos>m, o solo <minutos>m si dura menos de una hora
A15: 1.8 Las tres partes son obligatorias: si falta alguna, el script no rellena nada, deja la línea en su celda y avisa en el log
A16: 2. Ejecutar el script
A17: 2.1 Se hace en la pestaña Automatización -> Ver Scripts -> Scripts Recientes -> Create Tables -> Run
A18: 2.2 Este script está guardado en mi cuenta de OneDrive
A19: 2.3 Si por alguna razón no está visible, el script está también guardado en un repo de GitHub: https://github.com/miguelrr11/top1000albums
A20: 2.4 El script añade el álbum a Tabla Albums con año, subgéneros, duración y fecha de review (la de hoy, dd/mm/aaaa), y vacía la celda de la línea de info
... A27: 4. Hacer push en el repo de GitHub (el repo contiene el script pero también contiene el Excel)
H28: NOTAS: No es obligatorio ejecutar el script, se puede hacer cuando se quiera, no hay problema por hacer 5 reviews y luego ejecutarlo
A29: Resumen Hojas: | H29: - La fecha de review es el día en que ejecutas el script. Si hiciste la review otro día, cámbiala a mano en Tabla Albums.
A30: Hoja | B30: Tipo | C30: Razón | H30: - Para corregir un álbum ya reseñado: edita Tabla Albums directamente o escribe otra línea de info debajo del álbum.
A31: Albums | B31: MANUAL | C31: Se hacen las reviews | H31: La línea nueva sobrescribe año, subgéneros y duración, pero mantiene la fecha de review original.
A32: Tabla Albums | B32: SEMIAUTOMÁTICO | C32: Se rellana manualmente metadatos
A33: Tablas TOP | B33: AUTOMÁTICO
A34: TOP Canciones | B34: AUTOMÁTICO
A35: TOP Generos | B35: AUTOMÁTICO
A36: Mapeo Generos | B36: SEMIAUTOMÁTICO | C36: Se rellena manualmente subgeneros sin genero padre
A37: Resumen | B37: AUTOMÁTICO
A39: NOTAS
A40: El thirdEyeScore fue un intento de mejorar la nota de un álbum, en vez de ser simplemente la media de las canciones, también penaliza si
A41: la desviación es grande y recompensa álbumes con dieces
A43: La tabla de la hoja Tabla Albums se ordena por defecto por el valor thirdEyeScore, pero si se quiere ordenar por cualquier otra cosa, hay que
A44: quitar el asterisco del header de thirdeyescore, ponerlo en el header por el que se quiere ordenar la tabla, y ejecutar el script
A46: Algunas hojas no pasa nada si se modifican y otras no:
A47: Hoja | B47: Tipo | C47: Razón
A48: Albums | B48: VULNERABLE | C48: Es la fuente de verdad, si le pasa algo el resto de hojas se ven afectadas
A49: Tabla Albums | B49: SEMI-VULNERABLE | C49: Las columnas que se rellenan manualmente son vulnerables, si se eliminan, no hay manera de recuperarlas
A50: Tablas TOP | B50: INVULNERABLE | C50: Generada automaticamente
A51: TOP Canciones | B51: INVULNERABLE | C51: Generada automaticamente
A52: TOP Generos | B52: INVULNERABLE | C52: Generada automaticamente
A53: Mapeo Generos | B53: VULNERABLE | C53: Es la fuente de verdad de generos padre
A54: Resumen | B54: INVULNERABLE | C54: Generada automaticamente
A55: (Si algo es invulnerable significa que no pasa nada si modificas la hoja, el script la va a borrar igualmente para volver a generarla)
A57: Si por lo que sea has borrado algo que no deberías, puedes revertir el excel a través del repo de github
A59: Aclaración script: al empezar, el script guarda localmente los metadatos de la tabla de albums, y despues procede a BORRAR todas las hojas menos
B60: la de Albums y Mapeo Generos. Es decir, todo viene desde ese guardado local y la hoja Albums (y mapeo generos), de eso genera otra vez todas las hojas
A62: IMPORTANTE: no cambiar el nombre de las hojas
A64: NOTA: si el nombre del álbum contiene [OST], [LIVE] o [SINGLE], [EP], ese album no se incluirá en el calculo de determinadas tablas y/o estadisticas

Sheet Albums
A2: * TOOL - Lateralus | B2: =ROUND(SUM(B3:B14)/COUNT(B3:B14), 2) -> 10.11 | D2: * Radiohead - In Rainbows | E2: =ROUND(SUM(E3:E12)/COUNT(E3:E12), 2) -> 9.7 | G2: * Sweet Trip - You Will Never Know Why | H2: =ROUND(SUM(H3:H15)/COUNT(H3:H15), 2) -> 8.88 | J2: * The Alan Parsons Project - Eye In The Sky | K2: =ROUND(SUM(K3:K12)/COUNT(K3:K12), 2) -> 9.15 | M2: * Pink Floyd - The Dark Side Of The Moon | N2: =ROUND(SUM(N3:N12)/COUNT(N3:N12), 2) -> 9.61
A3: The Grudge | B3: 10.5 | D3: 15 Step | E3: 10 | G3: Conversation of Two | H3: 9 | J3: Sirius | K3: 9.5 | M3: Speak to Me
A4: Eon Blue Apocalypse | D4: Bodysnatchers | E4: 9 | G4: Air Supply | H4: 9 | J4: Eye In The Sky | K4: 10 | M4: Breath (In the Air) | N4: 9
A5: The Patient | B5: 10 | D5: Nude | E5: 10.5 | G5: Forever | H5: 8 | J5: Children of the Moon | K5: 8.5 | M5: On the Run | N5: 7.5
A6: Mantra | D6: Weird Fishes / Arpeggi | E6: 10.5 | G6: Acting | H6: 10 | J6: Gemini | K6: 8 | M6: Time | N6: 10.5
A7: Schsim | B7: 10.5 | D7: All I Need | E7: 10 | G7: Milk | H7: 10.5 | J7: Silence and I | K7: 10.5 | M7: The Great Gig in the Sky | N7: 10.5
A8: Parabol(a) | B8: 10.5 | D8: Faust Arp | E8: 8.5 | G8: Darkness | H8: 10.5 | J8: You're Gonna Get Your Fingers Burned | K8: 8.5 | M8: Money | N8: 10
A9: Ticks & Leeches | B9: 9.5 | D9: Reckoner | E9: 10.5 | G9: To the Moon | H9: 9 | J9: Psychobabble | K9: 9 | M9: Us and Them | N9: 10
A10: Lateralus | B10: 10.5 | D10: House Of Cards | E10: 9.5 | G10: Song About a Sea | H10: 7.5 | J10: Mammagamma | K10: 9 | M10: Any Colour You Like | N10: 9
A11: Disposition | B11: 9 | D11: Jigsaw Fallin Into Place | E11: 10.5 | G11: Song About a Sun | H11: 8 | J11: Step by Step | K11: 8.5 | M11: Brain Damage | N11: 10
A12: Reflection | B12: 10.5 | D12: Videotape | E12: 8 | G12: No Words to Be Found | H12: 8 | J12: Old And Wise | K12: 10 | M12: Eclipse | N12: 10
A13: Triad | B13: 10 | G13: Pretending | H13: 9
A14: Faaip De Oiad | D14: * Daft Punk - Discovery | E14: =ROUND(SUM(E15:E28)/COUNT(E15:E28), 2) -> 9 | G14: Misfortunes are Cruel | H14: 8.5 | J14: * Dire Straits - Brothers In Arms | K14: =ROUND(SUM(K15:K23)/COUNT(K15:K23), 2) -> 8.94 | M14: * Fleetwood Mac - Rumours | N14: =ROUND(SUM(N15:N26)/COUNT(N15:N26), 2) -> 8.71
D15: One More Time | E15: 9 | G15: Your World is Eternally Complete | H15: 8.5 | J15: So Far Away | K15: 9.5 | M15: Second Hand News | N15: 9
A16: * Metallica - Master Of Puppets | B16: =ROUND(SUM(B17:B24)/COUNT(B17:B24), 2) -> 9.25 | D16: Aerodynamic | E16: 10.5 | J16: Money For Nothing | K16: 10 | M16: Dreams | N16: 10
A17: Battery | B17: 9.5 | D17: Digital Love | E17: 10 | G17: * Massive Attack - Mezzanine | H17: =ROUND(SUM(H18:H28)/COUNT(H18:H28), 2) -> 8.77 | J17: Walk Of Life | K17: 9.5 | M17: Never Going Back Again | N17: 8
A18: Master Of Puppets | B18: 10 | D18: Harder, Better, Faster, Stonger | E18: 9.5 | G18: Angel | H18: 10 | J18: Your Latest Trick | K18: 9 | M18: Don't Stop | N18: 8.5
A19: The Thing That Should Not Be | B19: 8.5 | D19: Crescendolls | E19: 8.5 | G19: Risingson | H19: 9 | J19: Why Worry? | K19: 7.5 | M19: Go Your Own Way | N19: 8.5
A20: Welcome Home (Sanitarium) | B20: 10 | D20: Nightvision | G20: Teardrop | H20: 10 | J20: Ride Across The River | K20: 8 | M20: Songbird | N20: 7.5
A21: Disposable Heroes | B21: 8.5 | D21: Superheroes | E21: 9 | G21: Inertia Creeps | H21: 9 | J21: The Man's Too Strong | K21: 8.5 | M21: The Chain | N21: 10
A22: Leper Messiah | B22: 9 | D22: High Life | E22: 8 | G22: Exchange | H22: 8 | J22: One World | K22: 8 | M22: You Make Loving Fun | N22: 9
A23: Orion | B23: 10.5 | D23: Something About Us | E23: 10 | G23: Dissolved Girl | H23: 8.5 | J23: Brothers In Arms | K23: 10.5 | M23: I Don't Want to Know | N23: 8.5
A24: Damage, Inc. | B24: 8 | D24: Voyager | E24: 8.5 | G24: Man Next Door | H24: 8 | M24: Oh Daddy | N24: 7.5
D25: Veridis Quo | E25: 9.5 | G25: Black Milk | H25: 10 | J25: * Linkin Park - Hybrid Theory | K25: =ROUND(SUM(K26:K38)/COUNT(K26:K38), 2) -> 8.42 | M25: Gold Dust Woman | N25: 9
A26: * King Crimson - In The Court Of The Crimson King | B26: =ROUND(SUM(B27:B31)/COUNT(B27:B31), 2) -> 9.4 | D26: Short Circuit | E26: 8 | G26: Mezzazine | H26: 7.5 | J26: Papercut | K26: 10 | M26: Silver Springs | N26: 9
A27: 21st Century Schizoid Man | B27: 10 | D27: Face to Face | E27: 9 | G27: Group Four | H27: 8.5 | J27: One Step Closer | K27: 9.5
A28: I Talk To The Wind | B28: 9 | D28: Too Long | E28: 7.5 | G28: (Exchange) | H28: 8 | J28: With You | K28: 8.5 | M28: * The Strokes - The New Abnormal | N28: =ROUND(SUM(N29:N37)/COUNT(N29:N37), 2) -> 8.89
A29: Epitaph | B29: 10.5 | J29: Points of Authority | K29: 8.5 | M29: The Adults Are Talking | N29: 10
A30: Moonchild | B30: 8.5 | D30: * Opeth - Blackwater Park | E30: =ROUND(SUM(E31:E37)/COUNT(E31:E37), 2) -> 9.29 | G30: * TOOL - Ænima | H30: =ROUND(SUM(H31:H45)/COUNT(H31:H45), 2) -> 9.61 | J30: Crawling | K30: 9.5 | M30: Selfless | N30: 9
A31: The Court Of The Crimson King | B31: 9 | D31: The Lepper Affinity | E31: 9.5 | G31: Stinkfist | H31: 10 | J31: Runaway | K31: 8.5 | M31: Brooklyn Bridge To Chorus | N31: 8
D32: Bleak | E32: 10 | G32: Eulogy | H32: 10.5 | J32: By Myself | K32: 7.5 | M32: Bad Decisions | N32: 8.5
A33: * Radiohead - OK Computer | B33: =ROUND(SUM(B34:B45)/COUNT(B34:B45), 2) -> 9.68 | D33: Harvest | E33: 9 | G33: H. | H33: 10 | J33: In The End | K33: 9 | M33: Eternal Summer | N33: 9
A34: Airbag | B34: 9 | D34: The Drapery Falls | E34: 10.5 | G34: Useful Idiot | J34: A Place for My Head | K34: 8 | M34: At The Door | N34: 8
A35: Paranoid Android | B35: 10.5 | D35: Dirge For November | E35: 9.5 | G35: Forty Six & 2 | H35: 10.5 | J35: Forgotten | K35: 7 | M35: Why Are Sundays So Depressing | N35: 9
A36: Subterranean Homesick Alien | B36: 9.5 | D36: The Funeral Portrait | E36: 8 | G36: Message To Harry Manback | J36: Cure For The Itch | M36: Not The Same Anymore | N36: 8.5
A37: Exit Music (For a Film) | B37: 10 | D37: Blackwater Park | E37: 8.5 | G37: Hooker With A Penis | H37: 8.5 | J37: Pushing Me Away | K37: 7.5 | M37: Ode To The Mets | N37: 10
A38: Let Down | B38: 10.5 | G38: Intermission | J38: My December | K38: 7.5
A39: Karma Police | B39: 9.5 | D39: * Coldplay - X&Y | E39: =ROUND(SUM(E40:E52)/COUNT(E40:E52), 2) -> 8.65 | G39: Jimmy | H39: 9 | M39: * Have A Nice Life - Deathconsciousness | N39: =ROUND(SUM(N40:N52)/COUNT(N40:N52), 2) -> 9.21
A40: Fitter Happier | D40: Square One | E40: 8.5 | G40: Die Eir Von Satan | J40: * Alice In Chains - Dirt | K40: =ROUND(SUM(K41:K52)/COUNT(K41:K52), 2) -> 8.38 | M40: A Quick One Before the Eternal Worm Devours Connecticut | N40: 10
A41: Electioneering | B41: 9 | D41: What If | E41: 9 | G41: Pushit | H41: 10 | J41: Them Bones | K41: 9 | M41: Bloodhail | N41: 9.5
A42: Climbing Up the Walls | B42: 10 | D42: White Shadows | E42: 8.5 | G42: Cesaro Summability | J42: Dam That River | K42: 8.5 | M42: The Big Gloom | N42: 9
A43: No Surprises | B43: 10 | D43: Fix You | E43: 10 | G43: Ænema | H43: 9.5 | J43: Rain When I Die | K43: 9 | M43: Hunter | N43: 10.5
A44: Lucky | B44: 10 | D44: Talk | E44: 9 | G44: (-) Ions | J44: Down In A Hole | K44: 9.5 | M44: Telephony | N44: 8.5
A45: The Tourist | B45: 8.5 | D45: X&Y | E45: 8 | G45: Third Eye | H45: 8.5 | J45: Sickman | K45: 7.5 | M45: Who Would Leave Their Son Out in the Sun? | N45: 8
D46: Speed of Sound | E46: 9 | J46: Rooster | K46: 10 | M46: There Is No Food | N46: 8.5
A47: * Nas - Illmatic | B47: =ROUND(SUM(B48:B57)/COUNT(B48:B57), 2) -> 8.78 | D47: A Message | E47: 8.5 | G47: * Led Zeppelin - Led Zeppelin IV | H47: =ROUND(SUM(H48:H55)/COUNT(H48:H55), 2) -> 9.38 | J47: Junkhead | K47: 8 | M47: Waiting for Black Metal Records to Come in the Mail | N47: 8.5
A48: The Genesis | D48: Low | E48: 8 | G48: Black Dog | H48: 10 | J48: Dirt | K48: 7.5 | M48: Holy Fucking Shit: 40,000 | N48: 10
A49: N.Y. State of Mind | B49: 10 | D49: The Hardest Part | E49: 10 | G49: Rock and Roll | H49: 9.5 | J49: God Smack | K49: 7 | M49: The Future
A50: Life's a Bitch | B50: 9 | D50: Swallowed in the Sea | E50: 8.5 | G50: The Battle of Evermore | H50: 9.5 | J50: Hate To Feel | K50: 7 | M50: Deep, Deep | N50: 8
A51: The World Is Yours | B51: 9 | D51: Twisted Logic | E51: 8 | G51: Stairway to Heaven | H51: 10.5 | J51: Angry Chair | K51: 7.5 | M51: I Don't Love | N51: 10
A52: Halftime | B52: 8 | D52: Til Kingdom Come | E52: 7.5 | G52: Misty Mountain Hop | H52: 8.5 | J52: Would? | K52: 10 | M52: Earthmover | N52: 10
A53: Memory Lane | B53: 8 | G53: Four Sticks | H53: 8
A54: One Love | B54: 8 | D54: * Megadeth - Rust In Peace | E54: =ROUND(SUM(E55:E63)/COUNT(E55:E63), 2) -> 9 | G54: Going to California | H54: 9 | J54: * Joy Division - Unknown Pleasures | K54: =ROUND(SUM(K55:K64)/COUNT(K55:K64), 2) -> 8.35 | M54: * Radiohead - Kid A | N54: =ROUND(SUM(N55:N65)/COUNT(N55:N65), 2) -> 9.15
A55: One Time 4 Your Mind | B55: 8 | D55: Holy Wars…The Punishment Due | E55: 10 | G55: When the Levee Breaks | H55: 10 | J55: Disorder | K55: 10 | M55: Everything In Its Right Place | N55: 10
A56: Represent | B56: 10 | D56: Hangar 18 | E56: 9.5 | J56: Day of the Lords | K56: 9 | M56: Kid A | N56: 8.5
A57: It Ain't Hard to Tell | B57: 9 | D57: Take No Prisoners | E57: 8 | G57: * TOOL - Undertow | H57: =ROUND(SUM(H58:H67)/COUNT(H58:H67), 2) -> 8.35 | J57: Candidate | K57: 8 | M57: The National Anthem | N57: 9
D58: Five Magics | E58: 8.5 | G58: Intolerance | H58: 8 | J58: Insight | K58: 7 | M58: How to Disappear Completely | N58: 10.5
A59: * Wu Tang Clan - Enter the Wu-Tang (36 Chambers) | B59: =ROUND(SUM(B60:B69)/COUNT(B60:B69), 2) -> 8.33 | D59: Poison Was The Cure | E59: 9 | G59: Prison Sex | H59: 10 | J59: New Dawn Fades | K59: 8 | M59: Treefingers | N59: 8
A60: Shame On a Nuh | B60: 8 | D60: Lucretia | E60: 9 | G60: Sober | H60: 10 | J60: She's Lost Control | K60: 8 | M60: Optimistic | N60: 8.5
A61: Clan In Da Front | B61: 7 | D61: Tornado Of Souls | E61: 10.5 | G61: Bottom | H61: 9 | J61: Shadowplay | K61: 9 | M61: In Limbo | N61: 7.5
A62: Can It Be All So Simple | B62: 7.5 | D62: Dawn Patrol | E62: 8 | G62: Crawl Away | H62: 7 | J62: Wilderness | K62: 8 | M62: Idioteque | N62: 10
A63: Method Man | B63: 8.5 | D63: Rust In Peace…Polaris | E63: 8.5 | G63: Swamp Song | H63: 8.5 | J63: Interzone | K63: 8.5 | M63: Morning Bell | N63: 9
A64: Da Mystery of Cheesboxin' | B64: 9 | G64: Undertow | H64: 7.5 | J64: I Remember Nothing | K64: 8 | M64: Motion Picture Sountrack | N64: 10.5
A65: Wu-Tang Clan Ain't Nothing Ta F'Wit | B65: 9.5 | D65: * Mac Miller - Swimming | E65: =ROUND(SUM(E66:E78)/COUNT(E66:E78), 2) -> 8.46 | G65: 4º | H65: 10 | M65: Untitled
A66: C.R.E.A.M. | B66: 10 | D66: Come Back to Earth | E66: 8 | G66: Flood | H66: 7.5 | J66: * Riverside - Second Life Syndrome | K66: =ROUND(SUM(K67:K75)/COUNT(K67:K75), 2) -> 8
A67: Protet Ya Neck | B67: 8 | D67: Hurt Feelings | E67: 10 | G67: Disgustipated | H67: 6 | J67: After | M67: * Cocteau Twins - Heaven or Las Vegas | N67: =ROUND(SUM(N68:N77)/COUNT(N68:N77), 2) -> 9.05
A68: Tearz | B68: 7.5 | D68: What's the Use? | E68: 9 | J68: Volta-face | K68: 7 | M68: Cherry-coloured Funk | N68: 10.5
D69: Perfecto | E69: 8.5 | G69: * The Cure - Disintegration | H69: =ROUND(SUM(H70:H81)/COUNT(H70:H81), 2) -> 8.67 | J69: Conceiving You | K69: 8.5 | M69: Pitch the Baby | N69: 9.5
A70: * Hijos de la Ruina - Hijos de la ruina, vol. 3 | B70: =ROUND(SUM(B71:B77)/COUNT(B71:B77), 2) -> 7.29 | D70: Self Care | E70: 10 | G70: Plainsong | H70: 8.5 | J70: Second Life Syndrome | K70: 8.5 | M70: Iceblink Luck | N70: 8
A71: Nosotros | B71: 8 | D71: Wings | E71: 8 | G71: Pictures Of You | H71: 9 | J71: Artificial Smile | K71: 8 | M71: Fifty-fifty Clown | N71: 9
A72: Fuego, Fuego | B72: 7 | D72: Ladders | E72: 7.5 | G72: Closedown | H72: 8.5 | J72: I Turned You Down | K72: 8.5 | M72: Heaven or Las Vegas | N72: 10
A73: Cuestión de Fe | B73: 6.5 | D73: Small Worlds | E73: 9 | G73: Lovesong | H73: 10 | J73: Reality Dream III | K73: 8.5 | M73: I Wear Your Ring | N73: 8.5
A74: Sudores fríos | B74: 7 | D74: Conversation Pt. 1 | E74: 7 | G74: Last Dance | H74: 8.5 | J74: Dance With The Shadows | K74: 7.5 | M74: Fotzepolitic | N74: 8
A75: Más Alcohol | B75: 8 | D75: Dunno | E75: 8.5 | G75: Lullaby | H75: 10.5 | J75: Before | K75: 7.5 | M75: Wolf in the Breast | N75: 9
A76: A la tumba | B76: 7.5 | D76: Jet Fuel | E76: 8 | G76: Fascination Street | H76: 9 | M76: Road, River and Rail | N76: 8
A77: Dime que sí | B77: 7 | D77: 2009. | E77: 8.5 | G77: Prayers For Rain | H77: 8.5 | J77: * Megadeth - Megadeth | K77: =ROUND(SUM(K78:K88)/COUNT(K78:K88), 2) -> 7.77 | M77: Frou-frou Foxes in Midsummer Fires | N77: 10
D78: So It Goes | E78: 8 | G78: The Same Deep Water As You | H78: 7.5 | J78: Tipping Point | K78: 8.5
A79: * Radiohead - The Bends | B79: =ROUND(SUM(B80:B91)/COUNT(B80:B91), 2) -> 9.04 | G79: Disintegration | H79: 8.5 | J79: I Don't Care | K79: 8.5 | M79: * Porcupine Tree - In Absentia | N79: =ROUND(SUM(N80:N91)/COUNT(N80:N91), 2) -> 8.79
A80: Planet Telex | B80: 9 | D80: * Travis Scott - UTOPIA | E80: =ROUND(SUM(E81:E99)/COUNT(E81:E99), 2) -> 8.18 | G80: Homesick | H80: 8 | J80: Hey God?! | K80: 7.5 | M80: Blackest Eyes | N80: 10
A81: The Bends | B81: 9 | D81: HYAENA | E81: 10 | G81: Untitled | H81: 7.5 | J81: Let There Be Shred | K81: 7 | M81: Trains | N81: 10.5
A82: High And Dry | B82: 10 | D82: THANK GOD | E82: 8 | J82: Puppet Parade | K82: 8 | M82: Lips Of Ashes | N82: 8.5
A83: Fake Plastic Trees | B83: 10.5 | D83: MODERN JAM | E83: 8.5 | G83: * Dave - We're All Alone In This Together | H83: =ROUND(SUM(H84:H95)/COUNT(H84:H95), 2) -> 7.67 | J83: Another Bad Day | K83: 7.5 | M83: The Sound Of Muzak | N83: 9.5
A84: Bones | B84: 8.5 | D84: MY EYES | E84: 10 | G84: We're All Alone | H84: 8 | J84: Made To Kill | K84: 7.5 | M84: Gravity Eyelids | N84: 8
A85: (Nice Dream) | B85: 8.5 | D85: GOD'S COUNTRY | E85: 8.5 | G85: Verdansk | H85: 8 | J85: Obey The Call | K85: 7.5 | M85: Wedding Nails | N85: 8
A86: Just | B86: 9 | D86: SIRENS | E86: 7 | G86: Clash | H86: 8 | J86: I Am War | K86: 7 | M86: Prodigal | N86: 8.5
A87: My Iron Lung | B87: 8 | D87: METLDOWN | E87: 7.5 | G87: In The Fire | H87: 8.5 | J87: The Last Note | K87: 7.5 | M87: .3 | N87: 9
A88: Bullet Proof… I Wish I Was | B88: 8.5 | D88: FE!N | E88: 9 | G88: Three Rivers | H88: 7 | J88: Ride The Lightning (Bonus Track) | K88: 9 | M88: The Creator Has A Mastertape | N88: 8
A89: Black Star | B89: 9.5 | D89: DELRESTO (ECHOES) | E89: 7 | G89: System | H89: 8 | M89: Heartattack In A Layby | N89: 7
A90: Sulk | B90: 8 | D90: I KNOW? | E90: 8 | G90: Lazarus | H90: 7 | J90: * Porcupine Tree - Fear of a Blank Planet | K90: =ROUND(SUM(K91:K96)/COUNT(K91:K96), 2) -> 9.17 | M90: Strip The Soul | N90: 8.5
A91: Street Spirit (Fade Out) | B91: 10 | D91: TOPIA TWINS | E91: 7.5 | G91: Law Of Attraction | H91: 8 | J91: Fear of a Blank Planet | K91: 9.5 | M91: Collapse The Light Into Earth | N91: 10
D92: CIRCUS MAXIMUS | E92: 8.5 | G92: Both Sides Of A Smile | H92: 7 | J92: My Ashes | K92: 8.5
A93: * Opeth - Damnation | B93: =ROUND(SUM(B94:B101)/COUNT(B94:B101), 2) -> 8.81 | D93: PARASAIL | E93: 8 | G93: Twenty To One | H93: 8 | J93: Anesthetize | K93: 10.5 | M93: * Frank Ocean - Blonde | N93: =ROUND(SUM(N94:N110)/COUNT(N94:N110), 2) -> 8.5
A94: Windowpane | B94: 10 | D94: SKITZO | E94: 8 | G94: Heart Attack | H94: 6.5 | J94: Sentimental | K94: 9 | M94: Nikes | N94: 8
A95: In My Time of Need | B95: 9.5 | D95: LOST FOREVER | E95: 7 | G95: Survivor's Guilt | H95: 8 | J95: Way out of Here | K95: 9 | M95: Ivy | N95: 8
A96: Death Whispered a Lullaby | B96: 8.5 | D96: LOOOOVE | E96: 8.5 | J96: Sleep Together | K96: 8.5 | M96: Pink + White | N96: 9
A97: Closure | B97: 8 | D97: K-POP | E97: 8.5 | G97: * Radiohead - A Moon Shaped Pool | H97: =ROUND(SUM(H98:H108)/COUNT(H98:H109), 2) -> 8.77 | M97: Be Yourself
A98: Hope Leaves | B98: 9 | D98: TELEKINESIS | E98: 7 | G98: Burn The Witch | H98: 9.5 | J98: * TOOL - 10,000 Days | K98: =ROUND(SUM(K99:K109)/COUNT(K99:K109), 2) -> 9.61 | M98: Solo | N98: 8.5
A99: To Rid the Disease | B99: 8.5 | D99: TIL FURHTER NOTICE | E99: 9 | G99: Daydreaming | H99: 8.5 | J99: Vicarious | K99: 10.5 | M99: Skyline To | N99: 7.5
A100: Ending Credits | B100: 9.5 | G100: Decks Dark | H100: 8.5 | J100: Jambi | K100: 10 | M100: Self Control | N100: 9.5
A101: Weakness | B101: 7.5 | D101: * ZHU - GENERATIONWHY | E101: =ROUND(SUM(E102:E115)/COUNT(E102:E115), 2) -> 8.31 | G101: Desert Island Disk | H101: 8 | J101: Wings For Marie (Pt 1) | K101: 8.5 | M101: Good Guy
...

Sheet Tabla Albums
A1: ÁLBUMES
A2: # | B2: Artista | C2: Álbum | D2: Media | E2: 3rd EYE SCORE | F2: Mediana | G2: Desv. Típica | H2: Notas ≥10 | I2: Total Canciones | J2: Interludios | K2: Subgéneros | L2: Año | M2: Duración | N2: Fecha de review *
A3: 1 | B3: Prince | C3: Purple Rain | D3: 8.94 | E3: 8.95 | F3: 8.5 | G3: 0.96 | H3: 3 | I3: 9 | J3: 0 | K3: pop rock | L3: 1984 | M3: 43m | N3: 05/10/2026
A4: 2 | B4: Cocteau Twins | C4: Treasure | D4: 8.55 | E4: 8.47 | F4: 8.5 | G4: 0.52 | H4: 0 | I4: 10 | J4: 0 | K4: dream pop, ethereal wave | L4: 1984 | M4: 41m | N4: 04/10/2026
A5: 3 | B5: Electric Light Orchestra | C5: Discovery | D5: 8.56 | E5: 8.61 | F5: 8.5 | G5: 0.83 | H5: 1 | I5: 9 | J5: 0 | K5: pop rock | L5: 1979 | M5: 38m | N5: 02/10/2026
A6: 4 | B6: Queens of the Stone Age | C6: …Like Clockwork | D6: 8.95 | E6: 8.92 | F6: 9 | G6: 0.61 | H6: 2 | I6: 10 | J6: 0 | K6: alternative rock | L6: 2013 | M6: 46m | N6: 30/09/2026
A7: 5 | B7: Milo J | C7: La Vida Era Más Corta | D7: 8.17 | E7: 8.08 | F7: 8 | G7: 0.43 | H7: 0 | I7: 15 | J7: 0 | K7: art pop | L7: 2025 | M7: 48m | N7: 29/09/2026
A8: 6 | B8: Childish Gambino | C8: "Awaken, My Love!" | D8: 8.23 | E8: 8.21 | F8: 8 | G8: 1.23 | H8: 2 | I8: 11 | J8: 0 | K8: psychedelic soul, funk | L8: 2016 | M8: 49m | N8: 27/09/2026
A9: 7 | B9: The Caretaker | C9: Everywhere at the End of Time (Stage 3) | D9: 8.09 | E9: 8 | F9: 8 | G9: 0.57 | H9: 0 | I9: 16 | J9: 0 | K9: ambient, hauntology | L9: 2017 | M9: 45m | N9: 27/09/2026
A10: 8 | B10: The Caretaker | C10: Everywhere at the End of Time (Stage 4) | D10: 8 | E10: 7.96 | F10: 8 | G10: 0.35 | H10: 0 | I10: 4 | J10: 0 | K10: dark ambient, hauntology | L10: 2018 | M10: 1h 27m | N10: 27/09/2026
A11: 9 | B11: The Caretaker | C11: Everywhere at the End of Time (Stage 5) | D11: 7.88 | E11: 7.8 | F11: 7.75 | G11: 0.41 | H11: 0 | I11: 4 | J11: 0 | K11: dark ambient, noise | L11: 2018 | M11: 1h 28m | N11: 27/09/2026
A12: 10 | B12: The Caretaker | C12: Everywhere at the End of Time (Stage 6) | D12: 8.63 | E12: 8.5 | F12: 8.25 | G12: 0.82 | H12: 1 | I12: 4 | J12: 0 | K12: dark ambient, drone | L12: 2019 | M12: 1h 25m | N12: 27/09/2026
A13: 11 | B13: Napalm Death | C13: Scum | D13: 7.13 | E13: 6.97 | F13: 7 | G13: 1.08 | H13: 0 | I13: 28 | J13: 1 | K13: grindore | L13: 1987 | M13: 33m | N13: 26/09/2026
A14: 12 | B14: The Caretaker | C14: Everywhere at the End of Time (Stage 1) | D14: 8.17 | E14: 8.05 | F14: 8 | G14: 0.77 | H14: 1 | I14: 12 | J14: 0 | K14: ambient, hauntology | L14: 2016 | M14: 41m | N14: 26/09/2026
... A149: 147 | B149: Morbid Angel | C149: Altars of Madness | D149: 8.4 | E149: 8.3 | F149: 8.25 | G149: 0.73 | H149: 1 | I149: 10 | J149: 0 | K149: death metal | L149: 1989 | M149: 46m | N149: 26/05/2026
A150: 148 | B150: Foreigner | C150: 4 | D150: 8.6 | E150: 8.6 | F150: 8.25 | G150: 0.97 | H150: 2 | I150: 10 | J150: 0 | K150: aor, hard rock | L150: 1981 | M150: 41m | N150: 25/05/2026
A151: 149 | B151: Rainbow | C151: Rising | D151: 8.58 | E151: 8.5 | F151: 8.5 | G151: 0.79 | H151: 1 | I151: 6 | J151: 0 | K151: hard rock, heavy metal | L151: 1976 | M151: 33m | N151: 25/05/2026
A152: 150 | B152: A Perfect Circle | C152: Thirteenth Step | D152: 8.41 | E152: 8.24 | F152: 8 | G152: 0.95 | H152: 2 | I152: 12 | J152: 1 | K152: alternative rock, alternative metal | L152: 2003 | M152: 50m | N152: 24/05/2026
A153: 151 | B153: Deftones | C153: White Pony | D153: 8.96 | E153: 8.92 | F153: 9 | G153: 0.75 | H153: 3 | I153: 12 | J153: 0 | K153: alternative metal | L153: 2000 | M153: 52m | N153: 24/05/2026
A154: 152 | B154: Barry B | C154: CHATO | D154: 8.25 | E154: 8.18 | F154: 8.25 | G154: 0.6 | H154: 0 | I154: 12 | J154: 0 | K154: alt pop | L154: 2024 | M154: 34m | N154: 22/05/2026
A155: 153 | B155: black midi | C155: Hellfire | D155: 8.44 | E155: 8.39 | F155: 8.5 | G155: 0.55 | H155: 0 | I155: 10 | J155: 1 | K155: avant prog, brutal prog | L155: 2022 | M155: 38m | N155: 22/05/2026
A156: 154 | B156: The Beatles | C156: Revolver | D156: 8.39 | E156: 8.39 | F156: 8 | G156: 0.83 | H156: 2 | I156: 14 | J156: 0 | K156: pop rock, psychedelic pop | L156: 1966 | M156: 34m | N156: 21/05/2026
A157: 155 | B157: Pink Floyd | C157: The Wall | D157: 8.8 | E157: 8.97 | F157: 8.5 | G157: 0.73 | H157: 3 | I157: 26 | J157: 4 | K157: rock opera, art rock | L157: 1979 | M157: 1h 21m | N157: 21/05/2026
A158: 156 | B158: Slayyyter | C158: WOR$T GIRL IN AMERICA | D158: 8.65 | E158: 8.56 | F158: 8.5 | G158: 0.77 | H158: 2 | I158: 14 | J158: 1 | K158: electropop, electroclash | L158: 2026 | M158: 42m | N158: 20/05/2026
A159: 157 | B159: Dire Straits | C159: Love Over Gold | D159: 8.8 | E159: 8.81 | F159: 8.5 | G159: 0.93 | H159: 1 | I159: 5 | J159: 0 | K159: art rock | L159: 1982 | M159: 41m | N159: 19/05/2026
A160: 158 | B160: Justice | C160: Justice | D160: 8.63 | E160: 8.54 | F160: 8.5 | G160: 0.71 | H160: 2 | I160: 12 | J160: 0 | K160: french electro | L160: 2007 | M160: 48m | N160: 18/05/2026
A161: 159 | B161: System Of A Down | C161: Toxicity | D161: 8.83 | E161: 9 | F161: 8.5 | G161: 0.87 | H161: 3 | I161: 15 | J161: 0 | K161: alternative metal | L161: 2001 | M161: 44m | N161: 18/05/2026
A162: 160 | B162: Kanye West | C162: The College Dropout | D162: 8.73 | E162: 8.62 | F162: 8.5 | G162: 0.57 | H162: 1 | I162: 21 | J162: 6 | K162: chipmunk soul, pop rap | L162: 2004 | M162: 1h 16m | N162: 18/05/2026
... A337: 335 | B337: Opeth | C337: Blackwater Park | D337: 9.29 | E337: 9.44 | F337: 9.5 | G337: 0.8 | H337: 2 | I337: 7 | J337: 0 | K337: progressive metal, death metal | L337: 2001 | M337: 1h 16m | N337: 17/01/2026

Sheet Tablas TOP
A1: RESUMEN ARTISTAS REPETIDOS
A2: # | B2: Artista | C2: Álbumes | D2: Media | E2: 3rd EYE SCORE * | F2: Mediana | G2: Desv. Típica | H2: Notas ≥10 | I2: Total Canciones | J2: Interludios | K2: Subgéneros | L2: Año | M2: Duración | N2: Fecha de review
A3: 1 | B3: Fishmans | C3: 2 | D3: 9.75 | E3: 9.88 | F3: 9.63 | G3: 0.36 | H3: 3 | I3: 9 | J3: 0 | K3: neo psychedelic, dream pop, dowmtempo | L3: 1996 - 1997 | M3: 47m | N3: -
A4: 2 | B4: Pink Floyd | C4: 5 | D4: 9.35 | E4: 9.58 | F4: 9.35 | G4: 0.76 | H4: 16 | I4: 52 | J4: 5 | K4: progressive rock, psychedelic rock, art rock, rock opera | L4: 1971 - 1979 | M4: 51m | N4: -
A5: 3 | B5: TOOL | C5: 7 | D5: 9.16 | E5: 9.42 | F5: 9.39 | G5: 0.89 | H5: 26 | I5: 72 | J5: 16 | K5: progressive metal, alternative metal, post metal | L5: 1992 - 2019 | M5: 1h 9m | N5: -
A6: 4 | B6: Extremoduro | C6: 2 | D6: 9.21 | E6: 9.37 | F6: 9.38 | G6: 0.85 | H6: 5 | I6: 12 | J6: 0 | K6: hard rock, progressive rock, art rock | L6: 2008 - 2011 | M6: 44m | N6: -
A7: 5 | B7: Godspeed You! Black Emperor | C7: 3 | D7: 9.24 | E7: 9.28 | F7: 9.25 | G7: 0.32 | H7: 2 | I7: 12 | J7: 0 | K7: post rock | L7: 1997 - 2002 | M7: 1h 15m | N7: -
A8: 6 | B8: Led Zeppelin | C8: 3 | D8: 9.04 | E8: 9.06 | F8: 8.92 | G8: 0.92 | H8: 8 | I8: 26 | J8: 0 | K8: classic rock, folk rock, hard rock | L8: 1970 - 1973 | M8: 42m | N8: -
A9: 7 | B9: Sweet Trip | C9: 2 | D9: 8.94 | E9: 9.05 | F9: 9 | G9: 0.77 | H9: 5 | I9: 25 | J9: 0 | K9: dream pop, indie pop, idm, glitch pop | L9: 2003 - 2009 | M9: 1h 5m | N9: -
A10: 8 | B10: Yes | C10: 3 | D10: 8.91 | E10: 8.99 | F10: 9 | G10: 0.69 | H10: 3 | I10: 15 | J10: 1 | K10: progressive rock, symphonic prog | L10: 1971 - 1974 | M10: 40m | N10: -
A11: 9 | B11: Porcupine Tree | C11: 4 | D11: 8.91 | E11: 8.97 | F11: 8.75 | G11: 0.81 | H11: 7 | I11: 37 | J11: 0 | K11: progressive rock, progressive metal, post britpop | L11: 2000 - 2007 | M11: 59m | N11: -
A12: 10 | B12: Dire Straits | C12: 3 | D12: 8.86 | E12: 8.9 | F12: 8.67 | G12: 0.9 | H12: 5 | I12: 23 | J12: 0 | K12: classic rock, roots rock, blues rock, art rock | L12: 1978 - 1985 | M12: 45m | N12: -
A13: 11 | B13: C418 | C13: 2 | D13: 8.72 | E13: 8.9 | F13: 8.5 | G13: 0.94 | H13: 10 | I13: 54 | J13: 2 | K13: ambient, video game music | L13: 2011 - 2013 | M13: 1h 39m | N13: -
A14: 12 | B14: King Crimson | C14: 5 | D14: 8.9 | E14: 8.88 | F14: 8.75 | G14: 0.69 | H14: 5 | I14: 32 | J14: 0 | K14: progressive rock, art rock, avant prog | L14: 1969 - 2024 | M14: 44m | N14: -
... A57: 55 | B57: The Strokes | C57: 3 | D57: 7.71 | E57: 7.61 | F57: 7.67 | G57: 0.92 | H57: 3 | I57: 29 | J57: 0 | K57: garage rock, indie rock, garage rock revival | L57: 2001 - 2026 | M57: 41m | N57: -
A59: TOP 25 (sin repetir artistas y sin incluir OSTs, LIVEs y SINGLEs)
A60: # | B60: Artista | C60: Álbum | D60: Media | E60: 3rd EYE SCORE
A61: 1 | B61: TOOL | C61: Lateralus | D61: 10.11 | E61: 10.99
A62: 2 | B62: Fishmans | C62: LONG SEASON | D62: 10.5 | E62: 10.85
A63: 3 | B63: Yes | C63: Close to the Edge | D63: 10 | E63: 10.44
A64: 4 | B64: Radiohead | C64: In Rainbows | D64: 9.7 | E64: 10.37
A65: 5 | B65: Godspeed You! Black Emperor | C65: Lift Yr. Skinny Fists Like Antennas to Heaven! | D65: 9.88 | E65: 10.05
A66: 6 | B66: Pink Floyd | C66: The Dark Side Of The Moon | D66: 9.61 | E66: 10
A67: 7 | B67: Extremoduro | C67: La ley innata | D67: 9.5 | E67: 9.77
A68: 8 | B68: Led Zeppelin | C68: Led Zeppelin IV | D68: 9.38 | E68: 9.53
A69: 9 | B69: King Crimson | C69: In The Court Of The Crimson King | D69: 9.4 | E69: 9.46
A70: 10 | B70: Opeth | C70: Blackwater Park | D70: 9.29 | E70: 9.44
A71: 11 | B71: Black Sabbath | C71: Paranoid | D71: 9.31 | E71: 9.43
A72: 12 | B72: Metallica | C72: Master Of Puppets | D72: 9.25 | E72: 9.37
... A85: 25 | B85: Robe | C85: Mayéutica | D85: 9.08 | E85: 9.03
A87: TOP 25 (sin reglas)
A88: # | B88: Artista | C88: Álbum | D88: Media | E88: 3rd EYE SCORE
A89: 1 | B89: TOOL | C89: Lateralus | D89: 10.11 | E89: 10.99
A90: 2 | B90: Fishmans | C90: LONG SEASON | D90: 10.5 | E90: 10.85
A91: 3 | B91: Yes | C91: Close to the Edge | D91: 10 | E91: 10.44
A92: 4 | B92: Pink Floyd | C92: Wish You Were Here | D92: 10 | E92: 10.39
A93: 5 | B93: Radiohead | C93: In Rainbows | D93: 9.7 | E93: 10.37
A94: 6 | B94: Radiohead | C94: OK Computer | D94: 9.68 | E94: 10.07
A95: 7 | B95: Godspeed You! Black Emperor | C95: Lift Yr. Skinny Fists Like Antennas to Heaven! | D95: 9.88 | E95: 10.05
A96: 8 | B96: Pink Floyd | C96: The Dark Side Of The Moon | D96: 9.61 | E96: 10
A97: 9 | B97: TOOL | C97: 10,000 Days | D97: 9.61 | E97: 9.99
A98: 10 | B98: TOOL | C98: Ænima | D98: 9.61 | E98: 9.96
A99: 11 | B99: Extremoduro | C99: La ley innata | D99: 9.5 | E99: 9.77
A100: 12 | B100: Pink Floyd | C100: Animals | D100: 9.4 | E100: 9.55
... A113: 25 | B113: Opeth | C113: Ghost Reveries | D113: 9.13 | E113: 9.24
A118: TOP Progressive Rock (35 álbumes)
A119: # | B119: Artista | C119: Álbum | D119: Media | E119: 3rd EYE SCORE
A120: 1 | B120: Yes | C120: Close to the Edge | D120: 10 | E120: 10.44
A121: 2 | B121: Pink Floyd | C121: Wish You Were Here, The Dark Side Of The Moon, Animals | D121: 9.67 | E121: 9.98
A122: 3 | B122: Extremoduro | C122: La ley innata | D122: 9.5 | E122: 9.77
A123: 4 | B123: King Crimson | C123: In The Court Of The Crimson King, Red | D123: 9.35 | E123: 9.41
A124: 5 | B124: The Alan Parsons Project | C124: Eye In The Sky | D124: 9.15 | E124: 9.23
A126: TOP Progressive Metal (31 álbumes)
A127: # | B127: Artista | C127: Álbum | D127: Media | E127: 3rd EYE SCORE
A128: 1 | B128: TOOL | C128: Lateralus, 10,000 Days, Ænima, Salival [LIVE], Fear Inoculum | D128: 9.57 | E128: 9.98
A129: 2 | B129: Opeth | C129: Blackwater Park, Ghost Reveries, Deliverance, Still Life | D129: 9.07 | E129: 9.13
A130: 3 | B130: Porcupine Tree | C130: Fear of a Blank Planet, Deadwing | D130: 9.06 | E130: 9.14
A131: 4 | B131: Ne Obliviscaris | C131: Portal of I | D131: 9.14 | E131: 9.23
A132: 5 | B132: Meshuggah | C132: obZen | D132: 8.72 | E132: 8.84
A134: TOP Art Rock (27 álbumes)
A135: # | B135: Artista | C135: Álbum | D135: Media | E135: 3rd EYE SCORE
A136: 1 | B136: Pink Floyd | C136: Wish You Were Here, The Wall | D136: 9.4 | E136: 9.68
A137: 2 | B137: Radiohead | C137: In Rainbows, OK Computer, Kid A | D137: 9.51 | E137: 9.94
A138: 3 | B138: King Crimson | C138: In The Court Of The Crimson King, Red | D138: 9.35 | E138: 9.41
A139: 4 | B139: The Alan Parsons Project | C139: Eye In The Sky | D139: 9.15 | E139: 9.23
A140: 5 | B140: Extremoduro | C140: Material Defectuoso | D140: 8.92 | E140: 8.97
A142: TOP Alternative Rock (26 álbumes)
A143: # | B143: Artista | C143: Álbum | D143: Media | E143: 3rd EYE SCORE
A144: 1 | B144: Radiohead | C144: In Rainbows, OK Computer, The Bends | D144: 9.47 | E144: 9.86
A145: 2 | B145: Fiona Apple | C145: When The Pawn... | D145: 9 | E145: 8.95
A146: 3 | B146: Nirvana | C146: Nevermind | D146: 9 | E146: 8.92
A147: 4 | B147: Queens of the Stone Age | C147: …Like Clockwork | D147: 8.95 | E147: 8.92
A148: 5 | B148: Gorillaz | C148: Demon Days | D148: 8.88 | E148: 8.89
A150: TOP Alternative Metal (23 álbumes)
A151: # | B151: Artista | C151: Álbum | D151: Media | E151: 3rd EYE SCORE
A152: 1 | B152: TOOL | C152: Lateralus, 10,000 Days, Ænima, Salival [LIVE] | D152: 9.65 | E152: 10.12
A153: 2 | B153: System Of A Down | C153: Toxicity | D153: 8.83 | E153: 9
A154: 3 | B154: Deftones | C154: White Pony, Koi No Yokan, Around the Fur, Diamond Eyes | D154: 8.8 | E154: 8.79
A155: 4 | B155: Loathe | C155: I Let It in and It Took Everything | D155: 8.86 | E155: 8.83
A156: 5 | B156: Devin Townsend | C156: Ocean Machine | D156: 8.67 | E156: 8.56
A158: TOP Pop Rock (15 álbumes)
A159: # | B159: Artista | C159: Álbum | D159: Media | E159: 3rd EYE SCORE
A160: 1 | B160: Supertramp | C160: Even In The Quietest Moments..., Breakfast In America | D160: 8.91 | E160: 8.82
A161: 2 | B161: Coldplay | C161: Parachutes | D161: 8.94 | E161: 8.95
A162: 3 | B162: Prince | C162: Purple Rain | D162: 8.94 | E162: 8.95
A163: 4 | B163: The Beatles | C163: Sgt. Pepper's Lonely Hearts Club Band, Abbey Road | D163: 8.8 | E163: 8.84
A164: 5 | B164: Fleetwood Mac | C164: Rumours | D164: 8.71 | E164: 8.65
A166: TOP Indie Rock (15 álbumes)
A167: # | B167: Artista | C167: Álbum | D167: Media | E167: 3rd EYE SCORE
A168: 1 | B168: Geese | C168: Getting Killed | D168: 9 | E168: 8.96
A169: 2 | B169: Interpol | C169: Turn On The Bright Lights | D169: 8.91 | E169: 8.93
A170: 3 | B170: Panchiko | C170: D>E>A>T>H>M>E>T>A>L | D170: 8.93 | E170: 8.88
A171: 4 | B171: The Strokes | C171: The New Abnormal | D171: 8.89 | E171: 8.87
A172: 5 | B172: Pixies | C172: Doolittle | D172: 8.77 | E172: 8.79
A174: TOP Post Rock (14 álbumes)
A175: # | B175: Artista | C175: Álbum | D175: Media | E175: 3rd EYE SCORE
A176: 1 | B176: Godspeed You! Black Emperor | C176: Lift Yr. Skinny Fists Like Antennas to Heaven!, Yanqui U.X.O., F♯A♯∞ | D176: 9.24 | E176: 9.28
A177: 2 | B177: Talk Talk | C177: Spirit of Eden, Laughing Stock | D177: 8.96 | E177: 8.88
A178: 3 | B178: Slint | C178: Spiderland | D178: 8.92 | E178: 8.83
A179: 4 | B179: Boris | C179: flood | D179: 8.88 | E179: 8.81
...

Sheet TOP Canciones
A1: TOP 100 CANCIONES [10.5: 100] (máx. 2 por álbum) | G1: AJUSTES
A2: # | B2: Canción | C2: Álbum | D2: Artista | E2: Subgénero | G2: Canciones totales | H2: 100
A3: 1 | B3: Schsim | C3: Lateralus | D3: TOOL | E3: progressive metal, alternative metal | G3: Canciones por álbum | H3: 2
A4: 2 | B4: Lateralus | C4: Lateralus | D4: TOOL | E4: progressive metal, alternative metal | G4: Canciones por artista
A5: 3 | B5: LONG SEASON | C5: LONG SEASON | D5: Fishmans | E5: neo psychedelic, dream pop | G5: Randomizar en empate | H5: SI
A6: 4 | B6: Close to the Edge | C6: Close to the Edge | D6: Yes | E6: progressive rock | G6: Incluir Géneros
A7: 5 | B7: Siberian Khatru | C7: Close to the Edge | D7: Yes | E7: progressive rock | G7: Excluir Subgéneros
A8: 6 | B8: Wish You Were Here | C8: Wish You Were Here | D8: Pink Floyd | E8: progressive rock, art rock
A9: 7 | B9: Shine On You Crazy Diamond (Pts. 1-5) | C9: Wish You Were Here | D9: Pink Floyd | E9: progressive rock, art rock | G9: Géneros: separados por comas
A10: 8 | B10: Nude | C10: In Rainbows | D10: Radiohead | E10: art rock, alternative rock | G10: MAYÚSCULAS = género padre (ej: METAL)
A11: 9 | B11: Jigsaw Fallin Into Place | C11: In Rainbows | D11: Radiohead | E11: art rock, alternative rock | G11: minúsculas = subgénero (ej: thrash metal)
A12: 10 | B12: Paranoid Android | C12: OK Computer | D12: Radiohead | E12: art rock, alternative rock
A13: 11 | B13: Let Down | C13: OK Computer | D13: Radiohead | E13: art rock, alternative rock
A14: 12 | B14: Sleep | C14: Lift Yr. Skinny Fists Like Antennas to Heaven! | D14: Godspeed You! Black Emperor | E14: post rock
A15: 13 | B15: The Great Gig in the Sky | C15: The Dark Side Of The Moon | D15: Pink Floyd | E15: progressive rock, psychedelic rock
A16: 14 | B16: Time | C16: The Dark Side Of The Moon | D16: Pink Floyd | E16: progressive rock, psychedelic rock
A17: 15 | B17: Rosetta Stoned | C17: 10,000 Days | D17: TOOL | E17: progressive metal, alternative metal
A18: 16 | B18: Vicarious | C18: 10,000 Days | D18: TOOL | E18: progressive metal, alternative metal
A19: 17 | B19: Forty Six & 2 | C19: Ænima | D19: TOOL | E19: progressive metal, alternative metal
A20: 18 | B20: Eulogy | C20: Ænima | D20: TOOL | E20: progressive metal, alternative metal
A21: 19 | B21: Cuarto movimiento: la realidad | C21: La ley innata | D21: Extremoduro | E21: hard rock, progressive rock
A22: 20 | B22: Dogs | C22: Animals | D22: Pink Floyd | E22: progressive rock, psychedelic rock
A23: 21 | B23: Stairway to Heaven | C23: Led Zeppelin IV | D23: Led Zeppelin | E23: classic rock
... A102: 100 | B102: Xtal | C102: Selected Ambient Works 85-92 | D102: Aphex Twin | E102: ambient techno, idm

Sheet TOP Generos
A1: TOP Rock (157 álbumes)
A2: # | B2: Artista | C2: Álbum | D2: Media | E2: 3rd EYE SCORE
A3: 1 | B3: Fishmans | C3: LONG SEASON | D3: 10.5 | E3: 10.85
A4: 2 | B4: Yes | C4: Close to the Edge | D4: 10 | E4: 10.44
A5: 3 | B5: Pink Floyd | C5: Wish You Were Here | D5: 10 | E5: 10.39
A6: 4 | B6: Radiohead | C6: In Rainbows | D6: 9.7 | E6: 10.37
A7: 5 | B7: Radiohead | C7: OK Computer | D7: 9.68 | E7: 10.07
A8: 6 | B8: Godspeed You! Black Emperor | C8: Lift Yr. Skinny Fists Like Antennas to Heaven! | D8: 9.88 | E8: 10.05
A9: 7 | B9: Pink Floyd | C9: The Dark Side Of The Moon | D9: 9.61 | E9: 10
A10: 8 | B10: Extremoduro | C10: La ley innata | D10: 9.5 | E10: 9.77
A11: 9 | B11: Pink Floyd | C11: Animals | D11: 9.4 | E11: 9.55
A12: 10 | B12: Led Zeppelin | C12: Led Zeppelin IV | D12: 9.38 | E12: 9.53
A13: 11 | B13: King Crimson | C13: In The Court Of The Crimson King | D13: 9.4 | E13: 9.46
A14: 12 | B14: Black Sabbath | C14: Paranoid | D14: 9.31 | E14: 9.43
... A97: 95 | B97: The Clash | C97: London Calling | D97: 8.55 | E97: 8.6
A98: 96 | B98: Foreigner | C98: 4 | D98: 8.6 | E98: 8.6
A99: 97 | B99: Caspian | C99: Dust and Disquiet | D99: 8.67 | E99: 8.57
A100: 98 | B100: Blue Öyster Cult | C100: Fire of Unknown Origin | D100: 8.67 | E100: 8.57
A101: 99 | B101: Coldplay | C101: X&Y | D101: 8.65 | E101: 8.56
A102: 100 | B102: Radiohead | C102: Hail To the Thief | D102: 8.5 | E102: 8.56
A103: 101 | B103: Sigur Rós | C103: Ágætis byrjun | D103: 8.67 | E103: 8.56
A104: 102 | B104: Boris | C104: Pink | D104: 8.65 | E104: 8.56
A105: 103 | B105: Led Zeppelin | C105: Led Zeppelin III | D105: 8.6 | E105: 8.54
A106: 104 | B106: The Smile | C106: Wall Of Eyes | D106: 8.63 | E106: 8.53
A107: 105 | B107: Swans | C107: Soundtracks for the Blind | D107: 8.61 | E107: 8.52
A108: 106 | B108: La Paloma | C108: Una idea, pero es triste [EP] | D108: 8.6 | E108: 8.52
A109: 107 | B109: Beach House | C109: Bloom | D109: 8.6 | E109: 8.52
A110: 108 | B110: Oasis | C110: Definitely Maybe | D110: 8.59 | E110: 8.51
... A159: 157 | B159: Benson Boone | C159: American Heart | D159: 2.5 | E159: 2.39
A161: TOP Metal (92 álbumes)
A162: # | B162: Artista | C162: Álbum | D162: Media | E162: 3rd EYE SCORE
A163: 1 | B163: TOOL | C163: Lateralus | D163: 10.11 | E163: 10.99
A164: 2 | B164: TOOL | C164: 10,000 Days | D164: 9.61 | E164: 9.99
A165: 3 | B165: TOOL | C165: Ænima | D165: 9.61 | E165: 9.96
A166: 4 | B166: TOOL | C166: Salival [LIVE] | D166: 9.25 | E166: 9.53
A167: 5 | B167: Opeth | C167: Blackwater Park | D167: 9.29 | E167: 9.44
A168: 6 | B168: Black Sabbath | C168: Paranoid | D168: 9.31 | E168: 9.43
A169: 7 | B169: TOOL | C169: Fear Inoculum | D169: 9.29 | E169: 9.42
A170: 8 | B170: Metallica | C170: Master Of Puppets | D170: 9.25 | E170: 9.37
A171: 9 | B171: Opeth | C171: Ghost Reveries | D171: 9.13 | E171: 9.24
A172: 10 | B172: Porcupine Tree | C172: Fear of a Blank Planet | D172: 9.17 | E172: 9.23
A173: 11 | B173: Ne Obliviscaris | C173: Portal of I | D173: 9.14 | E173: 9.23
A174: 12 | B174: Metallica | C174: Ride The Lightning | D174: 9.13 | E174: 9.21
... A254: 92 | B254: Metallica | C254: St. Anger | D254: 3.68 | E254: 3.37
A256: TOP Electronic (50 álbumes)
A257: # | B257: Artista | C257: Álbum | D257: Media | E257: 3rd EYE SCORE
A258: 1 | B258: Radiohead | C258: Kid A | D258: 9.15 | E258: 9.37
A259: 2 | B259: Geometry Dash | C259: Geometry Dash [OST] | D259: 9.09 | E259: 9.33
A260: 3 | B260: Daft Punk | C260: Alive 2007 [LIVE] | D260: 9.08 | E260: 9.17
A261: 4 | B261: Daft Punk | C261: Discovery | D261: 9 | E261: 9.09
A262: 5 | B262: Boards of Canada | C262: Music Has The Right To Children | D262: 8.88 | E262: 9.04
A263: 6 | B263: Christopher Larkin | C263: Hollow Knight [OST] | D263: 8.67 | E263: 9
A264: 7 | B264: Sweet Trip | C264: Velocity: Design: Comfort. | D264: 9 | E264: 8.96
A265: 8 | B265: C418 | C265: Minecraft Volume Beta [OST] | D265: 8.72 | E265: 8.91
A266: 9 | B266: Fishmans | C266: 宇宙 日本 世田谷 | D266: 9 | E266: 8.91
A267: 10 | B267: C418 | C267: Minecraft Volume Alpha [OST] | D267: 8.72 | E267: 8.89
A268: 11 | B268: Portishead | C268: Dummy | D268: 8.91 | E268: 8.88
A269: 12 | B269: Boards of Canada | C269: Geogaddi | D269: 8.88 | E269: 8.84
... A307: 50 | B307: Radiohead | C307: The King Of Limbs | D307: 7.88 | E307: 7.74
A309: TOP Pop (33 álbumes)
A310: # | B310: Artista | C310: Álbum | D310: Media | E310: 3rd EYE SCORE
A311: 1 | B311: Sweet Trip | C311: You Will Never Know Why | D311: 8.88 | E311: 9.14
A312: 2 | B312: Supertramp | C312: Even In The Quietest Moments... | D312: 9.07 | E312: 9.02
A313: 3 | B313: Michael Jackson | C313: Thriller | D313: 9.06 | E313: 9.02
A314: 4 | B314: Sweet Trip | C314: Velocity: Design: Comfort. | D314: 9 | E314: 8.96
A315: 5 | B315: Gorillaz | C315: Demon Days | D315: 8.88 | E315: 8.89
A316: 6 | B316: The Smiths | C316: The Queen Is Dead | D316: 8.8 | E316: 8.87
A317: 7 | B317: Kate Bush | C317: Hounds of Love | D317: 8.86 | E317: 8.87
A318: 8 | B318: The Beatles | C318: Sgt. Pepper's Lonely Hearts Club Band | D318: 8.79 | E318: 8.86
A319: 9 | B319: The Stone Roses | C319: The Stone Roses | D319: 8.82 | E319: 8.83
A320: 10 | B320: Gorillaz | C320: Plastic Beach | D320: 8.67 | E320: 8.75
A321: 11 | B321: Air | C321: Moon Safari | D321: 8.75 | E321: 8.7
A322: 12 | B322: Mort Garson | C322: Mother Earth's Plantasia | D322: 8.75 | E322: 8.64
... A343: 33 | B343: Gorillaz | C343: The Mountain | D343: 8.11 | E343: 8
A345: TOP Hip Hop (25 álbumes)
A346: # | B346: Artista | C346: Álbum | D346: Media | E346: 3rd EYE SCORE
A347: 1 | B347: Kanye West | C347: Graduation | D347: 8.86 | E347: 8.92
A348: 2 | B348: Kanye West | C348: My Beautiful Dark Twisted Fantasy | D348: 8.82 | E348: 8.79
A349: 3 | B349: Nas | C349: Illmatic | D349: 8.78 | E349: 8.76
A350: 4 | B350: Nujabes | C350: Modal Soul | D350: 8.71 | E350: 8.76
A351: 5 | B351: Kendrick Lamar | C351: To Pimp A Butterfly | D351: 8.79 | E351: 8.71
A352: 6 | B352: Ms. Lauryn Hill | C352: The Miseducation of Lauryn Hill | D352: 8.8 | E352: 8.69
A353: 7 | B353: Joey Bada$$ | C353: 1999 (mixtape) | D353: 8.8 | E353: 8.68
A354: 8 | B354: Kanye West | C354: The College Dropout | D354: 8.73 | E354: 8.62
A355: 9 | B355: Nujabes | C355: Metaphorical Music | D355: 8.57 | E355: 8.49
A356: 10 | B356: Metro Boomin | C356: Spider-Man: Across The Spider-Verse [OST] | D356: 8.54 | E356: 8.49
A357: 11 | B357: Frank Ocean | C357: Blonde | D357: 8.5 | E357: 8.43
A358: 12 | B358: A Tribe Called Quest | C358: The Low End Theory | D358: 8.54 | E358: 8.41
... A371: 25 | B371: Hobo Johnson | C371: Hobo Johnson Alienates His Fanbase | D371: 0.81 | E371: 0.76
A373: TOP Ambient (16 álbumes)
A374: # | B374: Artista | C374: Álbum | D374: Media | E374: 3rd EYE SCORE
A375: 1 | B375: Christopher Larkin | C375: Hollow Knight [OST] | D375: 8.67 | E375: 9
A376: 2 | B376: David Bowie | C376: Low | D376: 9 | E376: 8.94
A377: 3 | B377: C418 | C377: Minecraft Volume Beta [OST] | D377: 8.72 | E377: 8.91
A378: 4 | B378: C418 | C378: Minecraft Volume Alpha [OST] | D378: 8.72 | E378: 8.89
A379: 5 | B379: Boris | C379: flood | D379: 8.88 | E379: 8.81
A380: 6 | B380: Steve Roach | C380: Structures From Silence | D380: 8.83 | E380: 8.71
A381: 7 | B381: Andrew Prahlow | C381: Outer Wilds [OST] | D381: 8.65 | E381: 8.69
A382: 8 | B382: Aphex Twin | C382: Selected Ambient Works Volume II | D382: 8.6 | E382: 8.66
A383: 9 | B383: The Caretaker | C383: Everywhere at the End of Time (Stage 6) | D383: 8.63 | E383: 8.5
...

Sheet Mapeo Generos
A1: SUBGÉNERO | B1: GÉNERO PADRE | C1: GÉNEROS ÚNICOS | E1: NOTAS
A2: alt pop | B2: pop | C2: ambient | E2: La columa de Subgenero se rellena automaticamente, coge los subgeneros de la tabla de la hoja Tabla Albums
A3: alternative dance | B3: electronic | C3: electronic
A4: alternative metal | B4: metal | C4: folk | E4: Manualmente se rellana la columa a su derecha, para asociar subgéneros con géneros padre
A5: alternative R&B | B5: r&b | C5: hip hop
A6: alternative rock | B6: rock | C6: industrial & noise | E6: Entonces si se ha incluido un subgenero nuevo, hay que introducir su asociación.
A7: ambient | B7: ambient | C7: jazz
A8: ambient pop | B8: pop | C8: metal | E8: Si ningún genero padre existente aplica (la tercera columna), se puede incluir un nuevo género padre,
A9: ambient techno | B9: electronic | C9: new age | E9: (automaticamente se pondrá en la tercera columna)
A10: andalusian rock | B10: rock | C10: pop
A11: aor | B11: rock | C11: psychedelia | E11: La tercera columna es simplemente de referencia, para saber que generos padres existen
A12: art pop | B12: pop | C12: punk
A13: art rock | B13: rock | C13: r&b
A14: atmospheric black metal | B14: metal | C14: regional music
A15: atmospheric sludge metal | B15: metal | C15: rock
A16: avant prog | B16: rock | C16: singer-songwriter
A17: baggy | B17: rock | C17: soundtrack
A18: big beat | B18: electronic
A19: black metal | B19: metal
A20: blackgaze | B20: metal
A21: blues rock | B21: rock
A22: boom bap | B22: hip hop
A23: britpop | B23: rock
A24: brutal death metal | B24: metal
A25: brutal prog | B25: metal
A26: chamber folk | B26: folk
A27: chipmunk soul | B27: hip hop
A28: city pop | B28: pop
A29: classic rock | B29: rock
... A165: funk | B165: rock
A166: ethereal wave

Sheet Graficos
AT1: Mes | AU1: Reviews acumuladas
AT2: 2026-01 | AU2: 42
AT3: 2026-02 | AU3: 78
AT4: 2026-03 | AU4: 119
AT5: 2026-04 | AU5: 152
AT6: 2026-05 | AU6: 192
AT7: 2026-06 | AU7: 232
AT8: 2026-07 | AU8: 271
AT9: 2026-08 | AU9: 289
AT10: 2026-09 | AU10: 316
AT11: 2026-10 | AU11: 319
AT14: Mes | AU14: Reviews del mes
AT15: 2026-01 | AU15: 42
AT16: 2026-02 | AU16: 36
AT17: 2026-03 | AU17: 41
AT18: 2026-04 | AU18: 33
AT19: 2026-05 | AU19: 40
AT20: 2026-06 | AU20: 40
AT21: 2026-07 | AU21: 39
AT22: 2026-08 | AU22: 18
AT23: 2026-09 | AU23: 27
AT24: 2026-10 | AU24: 3
AT27: Fecha de review | AU27: Media acumulada | AV27: 3rd EYE acumulado | AW27: Media últimos 20
AT28: 17/01/2026 | AU28: 8.88 | AV28: 9.14 | AW28: 8.88
AT29: 17/01/2026 | AU29: 9.02 | AV29: 9.19 | AW29: 9.02
AT30: 17/01/2026 | AU30: 9.01 | AV30: 9.15 | AW30: 9.01
AT31: 17/01/2026 | AU31: 8.99 | AV31: 9.12 | AW31: 8.99
AT32: 17/01/2026 | AU32: 8.95 | AV32: 9.03 | AW32: 8.95
AT33: 17/01/2026 | AU33: 8.86 | AV33: 8.92 | AW33: 8.86
AT34: 17/01/2026 | AU34: 8.86 | AV34: 8.91 | AW34: 8.86
AT35: 17/01/2026 | AU35: 8.92 | AV35: 8.98 | AW35: 8.92
AT36: 18/01/2026 | AU36: 8.99 | AV36: 9.09 | AW36: 8.99
AT37: 18/01/2026 | AU37: 9.02 | AV37: 9.12 | AW37: 9.02
AT38: 18/01/2026 | AU38: 9.05 | AV38: 9.15 | AW38: 9.05
AT39: 18/01/2026 | AU39: 9.07 | AV39: 9.16 | AW39: 9.07
... AT346: 05/10/2026 | AU346: 8.55 | AV346: 8.52 | AW346: 8.2
AT349: Mes | AU349: Media del mes
AT350: 2026-01 | AU350: 8.73
AT351: 2026-02 | AU351: 8.78
AT352: 2026-03 | AU352: 8.53
AT353: 2026-04 | AU353: 8.65
AT354: 2026-05 | AU354: 8.53
AT355: 2026-06 | AU355: 8.44
AT356: 2026-07 | AU356: 8.32
AT357: 2026-08 | AU357: 8.65
AT358: 2026-09 | AU358: 8.28
AT359: 2026-10 | AU359: 8.68
AT362: Nota | AU362: Frecuencia
AT363: 0.0 | AU363: 6
AT364: 0.5 | AU364: 0
AT365: 1.0 | AU365: 5
AT366: 1.5 | AU366: 1
AT367: 2.0 | AU367: 6
AT368: 2.5 | AU368: 1
AT369: 3.0 | AU369: 10
AT370: 3.5 | AU370: 2
AT371: 4.0 | AU371: 10
AT372: 4.5 | AU372: 0
AT373: 5.0 | AU373: 9
AT374: 5.5 | AU374: 2
... AT384: 10.5 | AU384: 126
AT387: Percentil | AU387: Nota
AT388: 0% | AU388: 0
AT389: 2% | AU389: 6
AT390: 4% | AU390: 7
AT391: 6% | AU391: 7
AT392: 8% | AU392: 7.5
AT393: 10% | AU393: 7.5
AT394: 12% | AU394: 7.5
AT395: 14% | AU395: 7.5
AT396: 16% | AU396: 8
AT397: 18% | AU397: 8
AT398: 20% | AU398: 8
AT399: 22% | AU399: 8
... AT438: 100% | AU438: 10.5
AT441: Nº de canciones | AU441: Álbumes
AT442: 1 | AU442: 1
AT443: 2 | AU443: 2
AT444: 3 | AU444: 4
AT445: 4 | AU445: 7
AT446: 5 | AU446: 11
AT447: 6 | AU447: 17
AT448: 7 | AU448: 18
AT449: 8 | AU449: 29
AT450: 9 | AU450: 34
AT451: 10 | AU451: 52
AT452: 11 | AU452: 34
AT453: 12 | AU453: 34
... AT471: 30 | AU471: 1
AT474: Década | AU474: Álbumes
AT475: 1960s | AU475: 6
AT476: 1970s | AU476: 33
AT477: 1980s | AU477: 31
AT478: 1990s | AU478: 75
AT479: 2000s | AU479: 77
AT480: 2010s | AU480: 47
AT481: 2020s | AU481: 50
AT484: Década | AU484: 3rd EYE SCORE medio
AT485: 1960s | AU485: 8.86
AT486: 1970s | AU486: 8.92
...

Sheet Resumen
A1: RESUMEN GLOBAL
A2: GENERAL
A3: Total álbumes | B3: 319
A4: Artistas únicos | B4: 196
A5: Total canciones | B5: 3385
A6: Canciones con nota | B6: 3230
A7: Interludios | B7: 155
A8: Canciones/álbum (media) | B8: 10.61
A9: % Interludios | B9: 0.0458
A11: NOTAS - TENDENCIA CENTRAL
A12: Media global | B12: 8.5
A13: Mediana global | B13: 8.5
A14: Moda (nota más frecuente) | B14: 8 (×790)
A16: NOTAS - DISPERSIÓN
A17: Desviación típica | B17: 1.16
A18: Coef. de variación | B18: 0.1368
A19: Rango (máx - mín) | B19: 10.5 (0 - 10.5)
A20: Rango intercuartílico (Q3-Q1) | B20: 1 (8 - 9)
A22: NOTAS - FORMA DE LA DISTRIBUCIÓN
A23: Asimetría (skewness) | B23: -2 ← sesgo alto
A24: Curtosis (excess) | B24: 11.21 ← colas pesadas
A26: DISTRIBUCIÓN POR RANGOS
A27: [0, 5) | B27: 41 (1.27%)
A28: [5, 7) | B28: 63 (1.95%)
A29: [7, 8) | B29: 397 (12.29%)
A30: [8, 9) | B30: 1513 (46.84%)
A31: [9, 10) | B31: 737 (22.82%)
A32: [10, 10.5] | B32: 479(14.83%)
A34: DESTACADOS
A35: Mejor álbum | B35: Fishmans - LONG SEASON (10.5)
A36: Peor álbum | B36: Hobo Johnson - Hobo Johnson Alienates His Fanbase (0.81)
A37: Más consistente (menor desv.) | B37: Lady Twostar - The Great Plains (σ=0.24)
A38: Más irregular (mayor desv.) | B38: Imagine Dragons - Evolve (σ=1.98)
A40: SUBGÉNEROS
A41: Álbumes con subgénero | B41: 319 de 319
A42: Subgéneros únicos | B42: 157
A43: Más frecuente | B43: progressive rock (35)
A44: Mejor media | B44: alt country (9.25)
A45: Peor media | B45: comedy rap (0.81)
A47: DESGLOSE POR SUBGÉNERO
A48: alt country | B48: 1 · media 9.25 · score 9.33
A49: classic rock | B49: 2 · media 9.16 · score 9.28
A50: psychedelic rock | B50: 4 · media 9.13 · score 9.27
A51: slowcore | B51: 3 · media 9.06 · score 9.15
A52: soul | B52: 1 · media 9.06 · score 9.1
A53: progressive soul | B53: 1 · media 9.06 · score 9.1
A54: contemporary r&b | B54: 1 · media 9.06 · score 9.02
A55: dance pop | B55: 1 · media 9.06 · score 9.02
A56: neo psychedelic | B56: 5 · media 9.04 · score 9.06
A57: country rock | B57: 2 · media 9.04 · score 9.09
A58: glitch pop | B58: 1 · media 9 · score 8.96
A59: dowmtempo | B59: 1 · media 9 · score 8.91
... A204: comedy rap | B204: 1 · media 0.81 · score 0.76
A206: GÉNEROS PADRE
A207: Álbumes con género padre | B207: 319 de 319
A208: Géneros padre únicos | B208: 16
A209: Más frecuente | B209: rock (153)
A210: Mejor media | B210: r&b (8.72)
A211: Peor media | B211: regional music (4.79)
A212: Mejor 3rd EYE SCORE | B212: jazz (8.68)
A213: Peor 3rd EYE SCORE | B213: regional music (4.62)
A214: Más variado (nº subgéneros) | B214: rock (47)
A216: DESGLOSE POR GÉNERO PADRE
A217: jazz | B217: 4 álb · 3 subg · media 8.72 · score 8.68
A218: r&b | B218: 6 álb · 7 subg · media 8.72 · score 8.67
A219: rock | B219: 153 álb · 47 subg · media 8.63 · score 8.62
A220: folk | B220: 5 álb · 5 subg · media 8.7 · score 8.61
A221: pop | B221: 32 álb · 14 subg · media 8.65 · score 8.6
A222: singer-songwriter | B222: 8 álb · 1 subg · media 8.66 · score 8.57
A223: metal | B223: 91 álb · 29 subg · media 8.56 · score 8.55
A224: electronic | B224: 41 álb · 26 subg · media 8.6 · score 8.54
A225: punk | B225: 11 álb · 4 subg · media 8.57 · score 8.53
A226: ambient | B226: 12 álb · 5 subg · media 8.44 · score 8.37
A227: new age | B227: 1 álb · 1 subg · media 8.4 · score 8.37
A228: psychedelia | B228: 1 álb · 2 subg · media 8.11 · score 8
... A232: regional music | B232: 1 álb · 1 subg · media 4.79 · score 4.62
A234: MEJOR ÁLBUM POR GÉNERO PADRE
A235: jazz | B235: Herbie Hancock - Head Hunters (9.03)
A236: r&b | B236: Marvin Gaye - What's Going On (9.1)
A237: rock | B237: Fishmans - LONG SEASON (10.85)
A238: folk | B238: Adrianne Lenker - songs (8.79)
A239: pop | B239: Sweet Trip - You Will Never Know Why (9.14)
A240: singer-songwriter | B240: Fiona Apple - When The Pawn... (8.95)
A241: metal | B241: TOOL - Lateralus (10.99)
A242: electronic | B242: Radiohead - Kid A (9.37)
A243: punk | B243: Interpol - Turn On The Bright Lights (8.93)
A244: ambient | B244: David Bowie - Low (8.94)
A245: new age | B245: Enigma - MCMXC a.D. (8.37)
A246: psychedelia | B246: Gorillaz - The Mountain (8)
... A250: regional music | B250: Bad Bunny - DeBÍ TiRAR MáS FOToS (4.62)
A252: AÑO
A253: Álbumes con año | B253: 319 de 319
A254: Año más antiguo | B254: 1966
A255: Año más reciente | B255: 2026
A256: Décadas con más álbumes | B256: 2000s (77)
A257: Década mejor puntuada | B257: 1970s (8.92)
A259: ÁLBUMES POR DÉCADA
A260: 1960s | B260: 6 álbumes · media 8.86
A261: 1970s | B261: 33 álbumes · media 8.92
A262: 1980s | B262: 31 álbumes · media 8.7
...

Sheet video
B1: song | C1: commentary | D1: genre | E1: album | F1: artist | G1: year
A2: 1 | B2: Close to the Edge | C2: Music doesn't get better than this | D2: =VLOOKUP(E2,'Tabla Albums'!C:L,9,FALSE) -> progressive rock | E2: Close to the Edge | F2: Yes | G2: 1972
A3: 2 | B3: Reflection | C3: TOOL is the closest thing I've ever had to a true spiritual experience | D3: =VLOOKUP(E3,'Tabla Albums'!C:L,9,FALSE) -> progressive metal, alternative metal | E3: Lateralus | F3: TOOL | G3: =VLOOKUP(E3,'Tabla Albums'!C:L,10,FALSE) -> 2001
A4: 3 | B4: Weird Fishes / Arpeggi | C4: There is nothing more beautiful in the entire world than this song. Makes me cry instantly. | D4: =VLOOKUP(E4,'Tabla Albums'!C:L,9,FALSE) -> art rock, alternative rock | E4: In Rainbows | F4: Radiohead | G4: =VLOOKUP(E4,'Tabla Albums'!C:L,10,FALSE) -> 2007
A5: 4 | B5: Cuarto movimiento: la realidad | C5: This album thouches my soul in places no other album can | D5: =VLOOKUP(E5,'Tabla Albums'!C:L,9,FALSE) -> hard rock, progressive rock | E5: La ley innata | F5: Extremoduro | G5: =VLOOKUP(E5,'Tabla Albums'!C:L,10,FALSE) -> 2008
A6: 5 | B6: Sleep | C6: Music so out of this world I don't feel like I deserve to listen to it | D6: =VLOOKUP(E6,'Tabla Albums'!C:L,9,FALSE) -> post rock | E6: Lift Yr. Skinny Fists Like Antennas to Heaven! | F6: Godspeed You! Black Emperor | G6: =VLOOKUP(E6,'Tabla Albums'!C:L,10,FALSE) -> 2000
A7: 6 | B7: Siberian Khatru | C7: The levels of dopamine this song gives me cannot be healthy | D7: =VLOOKUP(E7,'Tabla Albums'!C:L,9,FALSE) -> progressive rock | E7: Close to the Edge | F7: Yes | G7: =VLOOKUP(E7,'Tabla Albums'!C:L,10,FALSE) -> 1972
A8: 7 | B8: Ghost of Perdition | C8: The most complete metal song ever made. Masterpiece among masterpieces. | D8: =VLOOKUP(E8,'Tabla Albums'!C:L,9,FALSE) -> progressive metal, death metal | E8: Ghost Reveries | F8: Opeth | G8: =VLOOKUP(E8,'Tabla Albums'!C:L,10,FALSE) -> 2005
A9: 8 | B9: Pigs (Three Different Ones) | C9: Holy fucking solo. Pink Floyd's best album. | D9: =VLOOKUP(E9,'Tabla Albums'!C:L,9,FALSE) -> progressive rock, psychedelic rock | E9: Animals | F9: Pink Floyd | G9: =VLOOKUP(E9,'Tabla Albums'!C:L,10,FALSE) -> 1977
A10: 9 | B10: I Don't Love | C10: Why do I connect so deeply with depressing music if I'm such a happy person? | D10: =VLOOKUP(E10,'Tabla Albums'!C:L,9,FALSE) -> shoegaze, slowcore | E10: Deathconsciousness | F10: Have A Nice Life | G10: =VLOOKUP(E10,'Tabla Albums'!C:L,10,FALSE) -> 2008
A11: 10 | B11: Motion Picture Soundtrack | C11: I still don't know how toavoid crying to this song | D11: =VLOOKUP(E11,'Tabla Albums'!C:L,9,FALSE) -> art rock, electronic | E11: Kid A | F11: Radiohead | G11: =VLOOKUP(E11,'Tabla Albums'!C:L,10,FALSE) -> 2000
A12: 11 | B12: Eclipse | C12: Perfect closure of a perfect album | D12: =VLOOKUP(E12,'Tabla Albums'!C:L,9,FALSE) -> progressive rock, psychedelic rock | E12: The Dark Side Of The Moon | F12: Pink Floyd | G12: =VLOOKUP(E12,'Tabla Albums'!C:L,10,FALSE) -> 1973
A13: 12 | B13: Right In Two | C13: TOOL will always be my favorite band of all time | D13: =VLOOKUP(E13,'Tabla Albums'!C:L,9,FALSE) -> progressive metal, alternative metal | E13: 10,000 Days | F13: TOOL | G13: =VLOOKUP(E13,'Tabla Albums'!C:L,10,FALSE) -> 2006
A14: 13 | B14: Face of Melinda | C14: Once you acquire the taste for Opeth, there's no going back | D14: =VLOOKUP(E14,'Tabla Albums'!C:L,9,FALSE) -> progressive metal, death metal | E14: Still Life | F14: Opeth | G14: =VLOOKUP(E14,'Tabla Albums'!C:L,10,FALSE) -> 1999
... A26: 25 | B26: Way Out Of Here | C26: I'd put Anesthetize here but I already put it in my other top 100 songs video | D26: =VLOOKUP(E26,'Tabla Albums'!C:L,9,FALSE) -> progressive rock, progressive metal | E26: Fear of a Blank Planet | F26: Porcupine Tree | G26: =VLOOKUP(E26,'Tabla Albums'!C:L,10,FALSE) -> 2007
A27: 26 | B27: Tunnel of Love | C27: Their most emotional song, and my most listened song by them | D27: pop rock | E27: Tunnel of Love | F27: Dire Straits | G27: 1980
A28: 27 | B28: Fade to Black | C28: This was my favorite song of all time for a very long time | D28: =VLOOKUP(E28,'Tabla Albums'!C:L,9,FALSE) -> thrash metal | E28: Ride The Lightning | F28: Metallica | G28: =VLOOKUP(E28,'Tabla Albums'!C:L,10,FALSE) -> 1984
A29: 28 | B29: Windowlicker | C29: Electronic music's Stairway to Heaven | D29: =VLOOKUP(E29,'Tabla Albums'!C:L,9,FALSE) -> idm | E29: Windowlicker [SINGLE] | F29: Aphex Twin | G29: =VLOOKUP(E29,'Tabla Albums'!C:L,10,FALSE) -> 1995
A30: 29 | B30: Resurrections | C30: Celeste wouldn't be such a masterpiece if it weren't for its music | D30: videogame music | E30: Celest OST | F30: Lena Raine | G30: 2018
A31: 30 | B31: Indiscipline | C31: Insane drumming | D31: =VLOOKUP(E31,'Tabla Albums'!C:L,9,FALSE) -> progressive rock, art rock | E31: Discipline | F31: King Crimson | G31: =VLOOKUP(E31,'Tabla Albums'!C:L,10,FALSE) -> 1981
A32: 31 | B32: Somewhere I Belong | C32: The only kind of nu metal that I really dig | D32: =VLOOKUP(E32,'Tabla Albums'!C:L,9,FALSE) -> nu metal, rap metal | E32: Meteora | F32: Linkin Park | G32: =VLOOKUP(E32,'Tabla Albums'!C:L,10,FALSE) -> 2003
A33: 32 | B33: Si te vas… | C33: If Extremoduro were american, they'd be globally famous | D33: =VLOOKUP(E33,'Tabla Albums'!C:L,9,FALSE) -> art rock | E33: Material Defectuoso | F33: Extremoduro | G33: =VLOOKUP(E33,'Tabla Albums'!C:L,10,FALSE) -> 2011
A34: 33 | B34: They’ll Only Miss You When You Leave | C34: Those violins destroy me | D34: =VLOOKUP(E34,'Tabla Albums'!C:L,9,FALSE) -> slowcore | E34: Songs About Leaving | F34: Carissa's Wierd | G34: =VLOOKUP(E34,'Tabla Albums'!C:L,10,FALSE) -> 2002
A35: 34 | B35: Choral Chambers | C35: Best track of both games | D35: videogame music | E35: Hollow Knight: Silksong | F35: Christopher Larkin | G35: 2025
A36: 35 | B36: Mercy Mercy Me (The Ecology) | C36: Absolutely timeless | D36: =VLOOKUP(E36,'Tabla Albums'!C:L,9,FALSE) -> soul, progressive soul | E36: What's Going On | F36: Marvin Gaye | G36: =VLOOKUP(E36,'Tabla Albums'!C:L,10,FALSE) -> 1979
A37: 36 | B37: Eventually | C37: When the synth finally breaks free…. sooo damn good | D37: =VLOOKUP(E37,'Tabla Albums'!C:L,9,FALSE) -> neo psychedelic, indie | E37: Currents | F37: Tame Impala | G37: =VLOOKUP(E37,'Tabla Albums'!C:L,10,FALSE) -> 2015
A38: 37 | B38: Darkness | C38: I love every inch of this album with all my soul | D38: =VLOOKUP(E38,'Tabla Albums'!C:L,9,FALSE) -> dream pop, indie pop | E38: You Will Never Know Why | F38: Sweet Trip | G38: =VLOOKUP(E38,'Tabla Albums'!C:L,10,FALSE) -> 2009
A39: 38 | B39: Living Mice | C39: I can't think of a modern artist that influenced more childhoods | D39: =VLOOKUP(E39,'Tabla Albums'!C:L,9,FALSE) -> ambient, video game music | E39: Minecraft Volume Alpha [OST] | F39: C418 | G39: =VLOOKUP(E39,'Tabla Albums'!C:L,10,FALSE) -> 2011
A40: 39 | B40: Catch The Rainbow | C40: The bassline, the drumming, the slow pacing… masterpiece | D40: Psychedelic Rock | E40: Ritchie Blackmore's Rainbow | F40: Rainbow | G40: 1975
A41: 40 | B41: Alive | C41: Best grunge singer. Fight me. | D41: =VLOOKUP(E41,'Tabla Albums'!C:L,9,FALSE) -> grunge, alternative rock | E41: Ten | F41: Pearl Jam | G41: =VLOOKUP(E41,'Tabla Albums'!C:L,10,FALSE) -> 1991
A42: 41 | B42: Cloudbusting | C42: I wish I had just a fraction of Kate Bush's talent | D42: =VLOOKUP(E42,'Tabla Albums'!C:L,9,FALSE) -> art pop, progressive pop | E42: Hounds of Love | F42: Kate Bush | G42: =VLOOKUP(E42,'Tabla Albums'!C:L,10,FALSE) -> 1985
A43: 42 | B43: I Don't Want It | C43: The only guitar solo that always makes me cry | D43: =VLOOKUP(E43,'Tabla Albums'!C:L,9,FALSE) -> neo psychedelic, art rock | E43: Quebec | F43: Ween | G43: =VLOOKUP(E43,'Tabla Albums'!C:L,10,FALSE) -> 2003
A44: 43 | B44: Firth of Fifth | C44: Progressive rock at its finest | D44: =VLOOKUP(E44,'Tabla Albums'!C:L,9,FALSE) -> progressive rock, symphonic prog | E44: Selling England by the Pound | F44: Genesis | G44: =VLOOKUP(E44,'Tabla Albums'!C:L,10,FALSE) -> 1973
A45: 44 | B45: The Rain Song | C45: This song comes from Heaven | D45: =VLOOKUP(E45,'Tabla Albums'!C:L,9,FALSE) -> hard rock | E45: Houses of the Holy | F45: Led Zeppelin | G45: =VLOOKUP(E45,'Tabla Albums'!C:L,10,FALSE) -> 1973
A46: 45 | B46: Cry For Me | C46: Why is this so damn good | D46: =VLOOKUP(E46,'Tabla Albums'!C:L,9,FALSE) -> neo psychedelic, synthpop | E46: Imaginal Disk | F46: Magdalena Bay | G46: =VLOOKUP(E46,'Tabla Albums'!C:L,10,FALSE) -> 2024
A47: 46 | B47: Gimme Shelter | C47: Those voice cracks give me the biggest chills. Legendary track. | D47: =VLOOKUP(E47,'Tabla Albums'!C:L,9,FALSE) -> blues rock, country rock | E47: Let It Bleed | F47: The Rolling Stones | G47: =VLOOKUP(E47,'Tabla Albums'!C:L,10,FALSE) -> 1969
A48: 47 | B48: The Rainbow | C48: This is the purest definition of art | D48: =VLOOKUP(E48,'Tabla Albums'!C:L,9,FALSE) -> post rock, art rock | E48: Spirit of Eden | F48: Talk Talk | G48: =VLOOKUP(E48,'Tabla Albums'!C:L,10,FALSE) -> 1988
A49: 48 | B49: The Final Thing on My Mind | C49: Whole songs feels like a buildup that explodes beautifully | D49: =VLOOKUP(E49,'Tabla Albums'!C:L,9,FALSE) -> progressive rock | E49: Your Wilderness | F49: The Pineapple Thief | G49: =VLOOKUP(E49,'Tabla Albums'!C:L,10,FALSE) -> 2016
A50: 49 | B50: P.Y.T. (Pretty Young Thing) | C50: That high pitched voice in the background scratches my brain sooo good | D50: =VLOOKUP(E50,'Tabla Albums'!C:L,9,FALSE) -> contemporary r&b, dance pop | E50: Thriller | F50: Michael Jackson | G50: =VLOOKUP(E50,'Tabla Albums'!C:L,10,FALSE) -> 1982
A51: 50 | B51: I Want You (She's So Heavy) | C51: I'll never forget the first time I listened the outro of this song | D51: blues rock | E51: Abbey Road | F51: The Beatles | G51: =VLOOKUP(E51,'Tabla Albums'!C:L,10,FALSE) -> 1969
A52: 51 | B52: Girlfriend Is Better | C52: This didn't need to go that hard | D52: =VLOOKUP(E52,'Tabla Albums'!C:L,9,FALSE) -> new wave, post punk | E52: Speaking in Tongues | F52: Talking Heads | G52: =VLOOKUP(E52,'Tabla Albums'!C:L,10,FALSE) -> 1983
A53: 52 | B53: Rational Gaze | C53: I LIKE JUICE FINISH YOUR JUICE | D53: =VLOOKUP(E53,'Tabla Albums'!C:L,9,FALSE) -> djent, groove metal | E53: Nothing | F53: Meshuggah | G53: =VLOOKUP(E53,'Tabla Albums'!C:L,10,FALSE) -> 2002
A54: 53 | B54: Forget Her | C54: "My heart is frozen still as I try to find the will to forget her somehow" | D54: =VLOOKUP(E54,'Tabla Albums'!C:L,9,FALSE) -> alternative rock, singer songwriter | E54: Grace | F54: Jeff Buckley | G54: =VLOOKUP(E54,'Tabla Albums'!C:L,10,FALSE) -> 1994
A55: 54 | B55: Hey | C55: That bass sounds so nice | D55: =VLOOKUP(E55,'Tabla Albums'!C:L,9,FALSE) -> alternative rock, indie rock | E55: Doolittle | F55: Pixies | G55: =VLOOKUP(E55,'Tabla Albums'!C:L,10,FALSE) -> 1989
A56: 55 | B56: Peaches En Regalia | C56: So many iconic moments in just 4 minutes | D56: =VLOOKUP(E56,'Tabla Albums'!C:L,9,FALSE) -> jazz rock, jazz fusion | E56: Hot Rats | F56: Frank Zappa | G56: =VLOOKUP(E56,'Tabla Albums'!C:L,10,FALSE) -> 1969
A57: 56 | B57: Luv(sic.) pt3 | C57: I'll never ever get tired of this masterpiece | D57: =VLOOKUP(E57,'Tabla Albums'!C:L,9,FALSE) -> jazz rap, instrumental hip hop | E57: Modal Soul | F57: Nujabes | G57: =VLOOKUP(E57,'Tabla Albums'!C:L,10,FALSE) -> 2005
A58: 57 | B58: Acrid Avid Jam Shred | C58: There are very few artists that I consider to be genius. Aphex Twin is one of them. | D58: =VLOOKUP(E58,'Tabla Albums'!C:L,9,FALSE) -> idm | E58: …I Care Because You Do | F58: Aphex Twin | G58: =VLOOKUP(E58,'Tabla Albums'!C:L,10,FALSE) -> 1995
A59: 58 | B59: Luna Roja | C59: 10/10 shoegaze track. Unfortunate that it's not really known in the States. | D59: =VLOOKUP(E59,'Tabla Albums'!C:L,9,FALSE) -> shoegaze, alternative rock | E59: Dynamo | F59: Soda Stereo | G59: =VLOOKUP(E59,'Tabla Albums'!C:L,10,FALSE) -> 1992
A60: 59 | B60: Stationary Traveller | C60: Literally one of the best guitar solos I know. Insanely tasteful. | D60: symphonic prog | E60: Stationary Traveller | F60: Camel | G60: 1984
A61: 60 | B61: Mutilated Lips | C61: Once you learn the chorus, it will be stuck in your head forever | D61: =VLOOKUP(E61,'Tabla Albums'!C:L,9,FALSE) -> neo psychedelic, art rock | E61: The Mollusk | F61: Ween | G61: =VLOOKUP(E61,'Tabla Albums'!C:L,10,FALSE) -> 1997
A62: 61 | B62: Eriatarka | C62: Such a unique sounding prog rock band, they have so many materpieces | D62: =VLOOKUP(E62,'Tabla Albums'!C:L,9,FALSE) -> progressive rock, post hardcore | E62: Deloused in the Comatorium | F62: The Mars Volta | G62: =VLOOKUP(E62,'Tabla Albums'!C:L,10,FALSE) -> 2003
A63: 62 | B63: Nutshell | C63: Heavenly song that hurts like hell | D63: =VLOOKUP(E63,'Tabla Albums'!C:L,9,FALSE) -> grunge, acoustic rock | E63: Unplugged (AiC) [LIVE] | F63: Alice In Chains | G63: =VLOOKUP(E63,'Tabla Albums'!C:L,10,FALSE) -> 1996
A64: 63 | B64: Primer movimiento: Después de la catarsis | C64: One of the greatest artists to come out of Spain. Rest in peace Robe. | D64: =VLOOKUP(E64,'Tabla Albums'!C:L,9,FALSE) -> progressive rock | E64: Mayéutica | F64: Robe | G64: =VLOOKUP(E64,'Tabla Albums'!C:L,10,FALSE) -> 2021
A65: 64 | B65: Pictures of You | C65: A song with 2:30 minutes of intro. And not just any intro. | D65: =VLOOKUP(E65,'Tabla Albums'!C:L,9,FALSE) -> new wave, post punk | E65: Disintegration | F65: The Cure | G65: =VLOOKUP(E65,'Tabla Albums'!C:L,10,FALSE) -> 1989
A66: 65 | B66: Is It Really You? | C66: I have definitely not cried to this song. Definitely. | D66: =VLOOKUP(E66,'Tabla Albums'!C:L,9,FALSE) -> alternative metal, metalcore | E66: I Let It in and It Took Everything | F66: Loathe | G66: =VLOOKUP(E66,'Tabla Albums'!C:L,10,FALSE) -> 2020
A67: 66 | B67: Dayvan Cowboy | C67: Holy fucking goosebumps. These guys are on another level. | D67: =VLOOKUP(E67,'Tabla Albums'!C:L,9,FALSE) -> downtempo, folktronica | E67: The Campfire Headphase | F67: Boards of Canada | G67: =VLOOKUP(E67,'Tabla Albums'!C:L,10,FALSE) -> 2005
A68: 67 | B68: Mirage | C68: What a song. You don't even need lyrics | D68: jazz fusion | E68: Enigmatic Ocean | F68: Jean-Luc Ponty | G68: 1978
A69: 68 | B69: The Orb of Dreamers | C69: There is something so extremely magical about this song | D69: videogame music | E69: Little Big Planet OST | F69: Daniel Pemberton | G69: 2008
A70: 69 | B70: Riders on the Storm | C70: That rain sound effect is what makes this song so special to me | D70: =VLOOKUP(E70,'Tabla Albums'!C:L,9,FALSE) -> blues rock, psychedelic rock | E70: L.A. Woman | F70: The Doors | G70: =VLOOKUP(E70,'Tabla Albums'!C:L,10,FALSE) -> 1971
A71: 70 | B71: The art of dying | C71: The art of drumming | D71: =VLOOKUP(E71,'Tabla Albums'!C:L,9,FALSE) -> progressive metal, death metal | E71: The way of all flesh | F71: Gojira | G71: =VLOOKUP(E71,'Tabla Albums'!C:L,10,FALSE) -> 2008
A72: 71 | B72: The Stargate [Tablet I] | C72: If Pink Floyd made death metal | D72: =VLOOKUP(E72,'Tabla Albums'!C:L,9,FALSE) -> death metal, progressive metal | E72: Absolute Elsewhere | F72: Blood Incantation | G72: =VLOOKUP(E72,'Tabla Albums'!C:L,10,FALSE) -> 2024
A73: 72 | B73: To Forgive | C73: I don't why this song is so good, but it is | D73: =VLOOKUP(E73,'Tabla Albums'!C:L,9,FALSE) -> alternative rock, art rock | E73: Mellon Collie And The Infinite Sadness | F73: The Smashing Pumpkins | G73: =VLOOKUP(E73,'Tabla Albums'!C:L,10,FALSE) -> 1995
A74: 73 | B74: Supersonic | C74: That outro is SO DAMN GOOOOOD | D74: =VLOOKUP(E74,'Tabla Albums'!C:L,9,FALSE) -> britpop | E74: Definitely Maybe | F74: The Clash | G74: =VLOOKUP(E74,'Tabla Albums'!C:L,10,FALSE) -> 1994
A75: 74 | B75: The Noose | C75: I love how the drummer uses space in the grooves, it's so tight | D75: =VLOOKUP(E75,'Tabla Albums'!C:L,9,FALSE) -> alternative rock, alternative metal | E75: Thirteenth Step | F75: A Perfect Circle | G75: =VLOOKUP(E75,'Tabla Albums'!C:L,10,FALSE) -> 2003
A76: 75 | B76: Risk | C76: Perfect Deftones song, it has it all | D76: =VLOOKUP(E76,'Tabla Albums'!C:L,9,FALSE) -> alternative metal | E76: Diamond Eyes | F76: Deftones | G76: =VLOOKUP(E76,'Tabla Albums'!C:L,10,FALSE) -> 2010
A77: 76 | B77: Policy of Truth | C77: They don't make music like this anymore | D77: =VLOOKUP(E77,'Tabla Albums'!C:L,9,FALSE) -> synthpop | E77: Violator | F77: Depeche Mode | G77: =VLOOKUP(E77,'Tabla Albums'!C:L,10,FALSE) -> 1990
A78: 77 | B78: Tangerine | C78: This song hits me in a way no other song does | D78: =VLOOKUP(E78,'Tabla Albums'!C:L,9,FALSE) -> folk rock, hard rock | E78: Led Zeppelin III | F78: Led Zeppelin | G78: =VLOOKUP(E78,'Tabla Albums'!C:L,10,FALSE) -> 1970
A79: 78 | B79: Souvlaki Space Station | C79: Shoegaze is such a magical genre | D79: =VLOOKUP(E79,'Tabla Albums'!C:L,9,FALSE) -> dream pop, shoegaze | E79: Souvlaki | F79: Slowdive | G79: =VLOOKUP(E79,'Tabla Albums'!C:L,10,FALSE) -> 1993
A80: 79 | B80: The Rip | C80: Hauntingly beautiful | D80: folktronica | E80: Third | F80: Portishead | G80: =VLOOKUP(E80,'Tabla Albums'!C:L,10,FALSE) -> 2008
A81: 80 | B81: New Millennium Cyanide Christ | C81: It doesn't get much more metal than this. God I love Meshuggah | D81: =VLOOKUP(E81,'Tabla Albums'!C:L,9,FALSE) -> djent, technical thrash metal | E81: Chaosphere | F81: Meshuggah | G81: =VLOOKUP(E81,'Tabla Albums'!C:L,10,FALSE) -> 1998
A82: 81 | B82: Simple Boy | C82: That drum breakdown always reminds me of When The Leeve Breaks, so damn good | D82: =VLOOKUP(E82,'Tabla Albums'!C:L,9,FALSE) -> progressive rock, alternative metal | E82: Sound Awake | F82: Karnivool | G82: =VLOOKUP(E82,'Tabla Albums'!C:L,10,FALSE) -> 2009
A83: 82 | B83: Child of Vision | C83: That 3-minute long piano solo is the best thing Supertramp ever did | D83: =VLOOKUP(E83,'Tabla Albums'!C:L,9,FALSE) -> progressive pop, pop rock | E83: Breakfast In America | F83: Supertramp | G83: =VLOOKUP(E83,'Tabla Albums'!C:L,10,FALSE) -> 1979
A84: 83 | B84: When I'm Small | C84: What a gem of a song | D84: =VLOOKUP(E84,'Tabla Albums'!C:L,9,FALSE) -> indietronica | E84: Eyelid Movies | F84: Phantogram | G84: =VLOOKUP(E84,'Tabla Albums'!C:L,10,FALSE) -> 2010
A85: 84 | B85: Arcs of Command | C85: Criminally underrated post-rock track (and album) | D85: =VLOOKUP(E85,'Tabla Albums'!C:L,9,FALSE) -> post rock, post metal | E85: Dust and Disquiet | F85: Caspian | G85: =VLOOKUP(E85,'Tabla Albums'!C:L,10,FALSE) -> 2015
A86: 85 | B86: Cobra | C86: If you hate Geese you can click out of the video | D86: =VLOOKUP(E86,'Tabla Albums'!C:L,9,FALSE) -> art rock, indie rock | E86: Getting Killed | F86: Geese | G86: =VLOOKUP(E86,'Tabla Albums'!C:L,10,FALSE) -> 2025
A87: 86 | B87: Chocolate Matter | C87: Favorite album cover of all time | D87: =VLOOKUP(E87,'Tabla Albums'!C:L,9,FALSE) -> idm, glitch pop | E87: Velocity: Design: Comfort. | F87: Sweet Trip | G87: =VLOOKUP(E87,'Tabla Albums'!C:L,10,FALSE) -> 2003
A88: 87 | B88: Paper Bag | C88: "Hunger hurts but starving works when it costs too much to love." | D88: =VLOOKUP(E88,'Tabla Albums'!C:L,9,FALSE) -> singer songwriter, alternative rock | E88: When The Pawn... | F88: Fiona Apple | G88: =VLOOKUP(E88,'Tabla Albums'!C:L,10,FALSE) -> 1999
A89: 88 | B89: Sound and Vision | C89: The first time I found this album, I listened to it 5 times in a row | D89: =VLOOKUP(E89,'Tabla Albums'!C:L,9,FALSE) -> art rock, ambient | E89: Low | F89: David Bowie | G89: =VLOOKUP(E89,'Tabla Albums'!C:L,10,FALSE) -> 1977
A90: 89 | B90: Flowers | C90: Heavenly | D90: downtempo | E90: Let's Go | F90: In Love With A Ghost | G90: 2017
A91: 90 | B91: Bastard | C91: Insanely ahead of its time | D91: =VLOOKUP(E91,'Tabla Albums'!C:L,9,FALSE) -> progressive metal, alternative metal | E91: Ocean Machine | F91: Devin Townsend | G91: =VLOOKUP(E91,'Tabla Albums'!C:L,10,FALSE) -> 1997
A92: 91 | B92: come | C92: Devastating. Just like life itself sometimes. | D92: =VLOOKUP(E92,'Tabla Albums'!C:L,9,FALSE) -> singer songwriter, contemporary folk | E92: songs | F92: Adrianne Lenker | G92: =VLOOKUP(E92,'Tabla Albums'!C:L,10,FALSE) -> 2020
A93: 92 | B93: In The Shadow Of Our Pale Companion | C93: Genuinely one of the best metal songs ever recorded | D93: =VLOOKUP(E93,'Tabla Albums'!C:L,9,FALSE) -> post metal, folk metal | E93: The Mantle | F93: Agalloch | G93: =VLOOKUP(E93,'Tabla Albums'!C:L,10,FALSE) -> 2002
A94: 93 | B94: Pokka Pokka | C94: I can't get enough of this album | D94: =VLOOKUP(E94,'Tabla Albums'!C:L,9,FALSE) -> dream pop, dowmtempo | E94: 宇宙 日本 世田谷 | F94: Fishmans | G94: =VLOOKUP(E94,'Tabla Albums'!C:L,10,FALSE) -> 1997
A95: 94 | B95: In My Darkest Hour | C95: Peak thrash | D95: thrash metal | E95: So Far, So Good… So What! | F95: Megadeth | G95: 1988
A96: 95 | B96: Pillars | C96: So beautiful | D96: =VLOOKUP(E96,'Tabla Albums'!C:L,9,FALSE) -> midwest emo, indie rock | E96: How It Feels to Be Something On | F96: Sunny Day Real Estate | G96: =VLOOKUP(E96,'Tabla Albums'!C:L,10,FALSE) -> 1998
A97: 96 | B97: Laputa | C97: Imagine if that one guy never found the CD… | D97: =VLOOKUP(E97,'Tabla Albums'!C:L,9,FALSE) -> indie rock, dream pop | E97: D>E>A>T>H>M>E>T>A>L | F97: Panchiko | G97: =VLOOKUP(E97,'Tabla Albums'!C:L,10,FALSE) -> 2000
A98: 97 | B98: Supertwister | C98: This song being only 3 minutes long makes me so sad | D98: =VLOOKUP(E98,'Tabla Albums'!C:L,9,FALSE) -> symphonic prog, progressive rock | E98: Mirage | F98: Camel | G98: =VLOOKUP(E98,'Tabla Albums'!C:L,10,FALSE) -> 1974
A99: 98 | B99: Heartbeat City | C99: Sublime synth riff | D99: pop rock | E99: Heartbeat City | F99: The Cars | G99: 1984
A100: 99 | B100: Kindergarten | C100: Legendary album | D100: =VLOOKUP(E100,'Tabla Albums'!C:L,9,FALSE) -> alternative metal | E100: Angel Dust | F100: Faith No More | G100: =VLOOKUP(E100,'Tabla Albums'!C:L,10,FALSE) -> 1992
A101: 100 | B101: In Fiction | C101: It flows so damn well. Whole album is excellent. | D101: =VLOOKUP(E101,'Tabla Albums'!C:L,9,FALSE) -> atmospheric sludge metal, post metal | E101: Panopticon | F101: ISIS | G101: =VLOOKUP(E101,'Tabla Albums'!C:L,10,FALSE) -> 2004
A102: 101 | B102: Maggot Brain | C102: And they say guitars can't cry | D102: =VLOOKUP(E102,'Tabla Albums'!C:L,9,FALSE) -> funk rock, psychedelic rock | E102: Maggot Brain | F102: Funkadelic | G102: =VLOOKUP(E102,'Tabla Albums'!C:L,10,FALSE) -> 1971
A103: 102 | B103: Good Morning, Captain | C103: Whoever says this album is overrated is just plain wrong | D103: =VLOOKUP(E103,'Tabla Albums'!C:L,9,FALSE) -> post rock, post hardcore | E103: Spiderland | F103: Slint | G103: =VLOOKUP(E103,'Tabla Albums'!C:L,10,FALSE) -> 1991
A104: 103 | B104: flood III | C104: Not a single second wasted on this hour-long song | D104: =VLOOKUP(E104,'Tabla Albums'!C:L,9,FALSE) -> post rock, drone | E104: flood | F104: Boris | G104: =VLOOKUP(E104,'Tabla Albums'!C:L,10,FALSE) -> 2000
A105: 104 | B105: Devil In A New Dress | C105: If you talk during the guitar solo, I'm throwing you out of the window | D105: =VLOOKUP(E105,'Tabla Albums'!C:L,9,FALSE) -> pop rap, hip hop | E105: My Beautiful Dark Twisted Fantasy | F105: Kanye West | G105: =VLOOKUP(E105,'Tabla Albums'!C:L,10,FALSE) -> 2010
A106: 105 | B106: A Little God In My Hands | C106: Swans' music evokes such weird feelings in me | D106: =VLOOKUP(E106,'Tabla Albums'!C:L,9,FALSE) -> experimental rock, post rock | E106: To Be Kind | F106: Swans | G106: =VLOOKUP(E106,'Tabla Albums'!C:L,10,FALSE) -> 2014
A107: 106 | B107: Burnin' For You | C107: This song improves my mood every time I listen to it | D107: =VLOOKUP(E107,'Tabla Albums'!C:L,9,FALSE) -> hard rock, occult rock | E107: Fire of Unknown Origin | F107: Blue Öyster Cult | G107: =VLOOKUP(E107,'Tabla Albums'!C:L,10,FALSE) -> 1981
A108: 107 | B108: Evening Calm | C108: This is everything I want from a shoegaze song | D108: =VLOOKUP(E108,'Tabla Albums'!C:L,9,FALSE) -> shoegaze, space rock revival | E108: Another Sunny Day | F108: honeydip | G108: =VLOOKUP(E108,'Tabla Albums'!C:L,10,FALSE) -> 2000
A109: 108 | B109: Represent | C109: He indeed knew how to start that shit | D109: =VLOOKUP(E109,'Tabla Albums'!C:L,9,FALSE) -> old school hip hop, east coast hip hop | E109: Illmatic | F109: Nas | G109: =VLOOKUP(E109,'Tabla Albums'!C:L,10,FALSE) -> 1994
A110: 109 | B110: Red Silence | C110: So dreamy and ethereal | D110: =VLOOKUP(E110,'Tabla Albums'!C:L,9,FALSE) -> singer songwriter, chamber folk | E110: Windswept Adan | F110: Ichiko Aoba | G110: =VLOOKUP(E110,'Tabla Albums'!C:L,10,FALSE) -> 2020
A111: 110 | B111: For A Better Day | C111: Banger | D111: dance pop, house | E111: Stories | F111: Avicii | G111: 2015
...
